{"metadata": {"dbt_schema_version": "https://schemas.getdbt.com/dbt/run-results/v4.json", "dbt_version": "1.6.3", "generated_at": "2023-09-25T13:12:12.533482Z", "invocation_id": "1d138273-2451-4b97-8e61-d1f3271b122e", "env": {}}, "results": [{"status": "success", "timing": [{"name": "compile", "started_at": "2023-09-25T13:11:54.875642Z", "completed_at": "2023-09-25T13:11:54.880999Z"}, {"name": "execute", "started_at": "2023-09-25T13:11:54.881375Z", "completed_at": "2023-09-25T13:11:54.922673Z"}], "thread_id": "Thread-1 (worker)", "execution_time": 0.05280423164367676, "adapter_response": {"_message": "OK"}, "message": "OK", "failures": null, "unique_id": "model.etl_synthea_dbt.all_visits"}, {"status": "success", "timing": [{"name": "compile", "started_at": "2023-09-25T13:11:54.930174Z", "completed_at": "2023-09-25T13:11:54.932914Z"}, {"name": "execute", "started_at": "2023-09-25T13:11:54.933266Z", "completed_at": "2023-09-25T13:11:54.960306Z"}], "thread_id": "Thread-1 (worker)", "execution_time": 0.037756919860839844, "adapter_response": {"_message": "OK"}, "message": "OK", "failures": null, "unique_id": "model.etl_synthea_dbt.cdm_source"}, {"status": "success", "timing": [{"name": "compile", "started_at": "2023-09-25T13:11:54.969468Z", "completed_at": "2023-09-25T13:11:54.972997Z"}, {"name": "execute", "started_at": "2023-09-25T13:11:54.973519Z", "completed_at": "2023-09-25T13:11:56.373881Z"}], "thread_id": "Thread-1 (worker)", "execution_time": 1.4141747951507568, "adapter_response": {"_message": "OK"}, "message": "OK", "failures": null, "unique_id": "model.etl_synthea_dbt.person"}, {"status": "success", "timing": [{"name": "compile", "started_at": "2023-09-25T13:11:56.385150Z", "completed_at": "2023-09-25T13:11:56.386914Z"}, {"name": "execute", "started_at": "2023-09-25T13:11:56.387255Z", "completed_at": "2023-09-25T13:11:56.441933Z"}], "thread_id": "Thread-1 (worker)", "execution_time": 0.07154726982116699, "adapter_response": {"_message": "OK"}, "message": "OK", "failures": null, "unique_id": "model.etl_synthea_dbt.provider"}, {"status": "success", "timing": [{"name": "compile", "started_at": "2023-09-25T13:11:56.458104Z", "completed_at": "2023-09-25T13:11:56.460372Z"}, {"name": "execute", "started_at": "2023-09-25T13:11:56.460719Z", "completed_at": "2023-09-25T13:11:56.736990Z"}], "thread_id": "Thread-1 (worker)", "execution_time": 0.284714937210083, "adapter_response": {"_message": "OK"}, "message": "OK", "failures": null, "unique_id": "model.etl_synthea_dbt.source_to_source_vocab_map"}, {"status": "success", "timing": [{"name": "compile", "started_at": "2023-09-25T13:11:56.744426Z", "completed_at": "2023-09-25T13:11:56.747062Z"}, {"name": "execute", "started_at": "2023-09-25T13:11:56.747420Z", "completed_at": "2023-09-25T13:11:57.102734Z"}], "thread_id": "Thread-1 (worker)", "execution_time": 0.3644440174102783, "adapter_response": {"_message": "OK"}, "message": "OK", "failures": null, "unique_id": "model.etl_synthea_dbt.source_to_standard_vocab_map"}, {"status": "success", "timing": [{"name": "compile", "started_at": "2023-09-25T13:11:57.109999Z", "completed_at": "2023-09-25T13:11:57.111869Z"}, {"name": "execute", "started_at": "2023-09-25T13:11:57.112208Z", "completed_at": "2023-09-25T13:11:57.129429Z"}], "thread_id": "Thread-1 (worker)", "execution_time": 0.025254011154174805, "adapter_response": {"_message": "OK"}, "message": "OK", "failures": null, "unique_id": "model.etl_synthea_dbt.assign_all_visit_ids"}, {"status": "pass", "timing": [{"name": "compile", "started_at": "2023-09-25T13:11:57.136698Z", "completed_at": "2023-09-25T13:11:57.143124Z"}, {"name": "execute", "started_at": "2023-09-25T13:11:57.143515Z", "completed_at": "2023-09-25T13:11:57.156382Z"}], "thread_id": "Thread-1 (worker)", "execution_time": 0.022400856018066406, "adapter_response": {"_message": "OK"}, "message": null, "failures": 0, "unique_id": "test.etl_synthea_dbt.not_null_person_year_of_birth.03ea95e466"}, {"status": "pass", "timing": [{"name": "compile", "started_at": "2023-09-25T13:11:57.160248Z", "completed_at": "2023-09-25T13:11:57.164825Z"}, {"name": "execute", "started_at": "2023-09-25T13:11:57.165298Z", "completed_at": "2023-09-25T13:11:57.175305Z"}], "thread_id": "Thread-1 (worker)", "execution_time": 0.018399953842163086, "adapter_response": {"_message": "OK"}, "message": null, "failures": 0, "unique_id": "test.etl_synthea_dbt.relationships_person_ethnicity_source_concept_id__concept_id__source_vocab_concept_.c1e57c3f06"}, {"status": "pass", "timing": [{"name": "compile", "started_at": "2023-09-25T13:11:57.179868Z", "completed_at": "2023-09-25T13:11:57.182914Z"}, {"name": "execute", "started_at": "2023-09-25T13:11:57.183301Z", "completed_at": "2023-09-25T13:11:57.193067Z"}], "thread_id": "Thread-1 (worker)", "execution_time": 0.01614093780517578, "adapter_response": {"_message": "OK"}, "message": null, "failures": 0, "unique_id": "test.etl_synthea_dbt.relationships_person_gender_source_concept_id__concept_id__source_vocab_concept_.871883de16"}, {"status": "pass", "timing": [{"name": "compile", "started_at": "2023-09-25T13:11:57.196834Z", "completed_at": "2023-09-25T13:11:57.199807Z"}, {"name": "execute", "started_at": "2023-09-25T13:11:57.200168Z", "completed_at": "2023-09-25T13:11:57.210041Z"}], "thread_id": "Thread-1 (worker)", "execution_time": 0.015851974487304688, "adapter_response": {"_message": "OK"}, "message": null, "failures": 0, "unique_id": "test.etl_synthea_dbt.relationships_person_race_source_concept_id__concept_id__source_vocab_concept_.cd59f4fb08"}, {"status": "pass", "timing": [{"name": "compile", "started_at": "2023-09-25T13:11:57.213993Z", "completed_at": "2023-09-25T13:11:57.216547Z"}, {"name": "execute", "started_at": "2023-09-25T13:11:57.216926Z", "completed_at": "2023-09-25T13:11:57.225650Z"}], "thread_id": "Thread-1 (worker)", "execution_time": 0.014492034912109375, "adapter_response": {"_message": "OK"}, "message": null, "failures": 0, "unique_id": "test.etl_synthea_dbt.not_null_provider_provider_id.3b46670424"}, {"status": "pass", "timing": [{"name": "compile", "started_at": "2023-09-25T13:11:57.229260Z", "completed_at": "2023-09-25T13:11:57.232777Z"}, {"name": "execute", "started_at": "2023-09-25T13:11:57.233144Z", "completed_at": "2023-09-25T13:11:57.241546Z"}], "thread_id": "Thread-1 (worker)", "execution_time": 0.015017032623291016, "adapter_response": {"_message": "OK"}, "message": null, "failures": 0, "unique_id": "test.etl_synthea_dbt.unique_provider_provider_id.b08928e435"}, {"status": "success", "timing": [{"name": "compile", "started_at": "2023-09-25T13:11:57.245332Z", "completed_at": "2023-09-25T13:11:57.247210Z"}, {"name": "execute", "started_at": "2023-09-25T13:11:57.247590Z", "completed_at": "2023-09-25T13:11:57.263879Z"}], "thread_id": "Thread-1 (worker)", "execution_time": 0.02399277687072754, "adapter_response": {"_message": "OK"}, "message": "OK", "failures": null, "unique_id": "model.etl_synthea_dbt.final_visit_ids"}, {"status": "success", "timing": [{"name": "compile", "started_at": "2023-09-25T13:11:57.270992Z", "completed_at": "2023-09-25T13:11:57.273002Z"}, {"name": "execute", "started_at": "2023-09-25T13:11:57.273338Z", "completed_at": "2023-09-25T13:11:57.293131Z"}], "thread_id": "Thread-1 (worker)", "execution_time": 0.02828383445739746, "adapter_response": {"_message": "OK"}, "message": "OK", "failures": null, "unique_id": "model.etl_synthea_dbt.death"}, {"status": "success", "timing": [{"name": "compile", "started_at": "2023-09-25T13:11:57.300557Z", "completed_at": "2023-09-25T13:11:57.303649Z"}, {"name": "execute", "started_at": "2023-09-25T13:11:57.304000Z", "completed_at": "2023-09-25T13:11:57.323114Z"}], "thread_id": "Thread-1 (worker)", "execution_time": 0.029484987258911133, "adapter_response": {"_message": "OK"}, "message": "OK", "failures": null, "unique_id": "model.etl_synthea_dbt.observation_period"}, {"status": "success", "timing": [{"name": "compile", "started_at": "2023-09-25T13:11:57.331595Z", "completed_at": "2023-09-25T13:11:57.334239Z"}, {"name": "execute", "started_at": "2023-09-25T13:11:57.334623Z", "completed_at": "2023-09-25T13:11:57.494864Z"}], "thread_id": "Thread-1 (worker)", "execution_time": 0.16933178901672363, "adapter_response": {"_message": "OK"}, "message": "OK", "failures": null, "unique_id": "model.etl_synthea_dbt.device_exposure"}, {"status": "success", "timing": [{"name": "compile", "started_at": "2023-09-25T13:11:57.502294Z", "completed_at": "2023-09-25T13:11:57.505592Z"}, {"name": "execute", "started_at": "2023-09-25T13:11:57.505933Z", "completed_at": "2023-09-25T13:11:57.683953Z"}], "thread_id": "Thread-1 (worker)", "execution_time": 0.18890094757080078, "adapter_response": {"_message": "OK"}, "message": "OK", "failures": null, "unique_id": "model.etl_synthea_dbt.drug_exposure"}, {"status": "success", "timing": [{"name": "compile", "started_at": "2023-09-25T13:11:57.692537Z", "completed_at": "2023-09-25T13:11:57.695924Z"}, {"name": "execute", "started_at": "2023-09-25T13:11:57.696282Z", "completed_at": "2023-09-25T13:11:57.876771Z"}], "thread_id": "Thread-1 (worker)", "execution_time": 0.19138813018798828, "adapter_response": {"_message": "OK"}, "message": "OK", "failures": null, "unique_id": "model.etl_synthea_dbt.measurement"}, {"status": "success", "timing": [{"name": "compile", "started_at": "2023-09-25T13:11:57.885258Z", "completed_at": "2023-09-25T13:11:57.888966Z"}, {"name": "execute", "started_at": "2023-09-25T13:11:57.889297Z", "completed_at": "2023-09-25T13:11:58.090979Z"}], "thread_id": "Thread-1 (worker)", "execution_time": 0.21439099311828613, "adapter_response": {"_message": "OK"}, "message": "OK", "failures": null, "unique_id": "model.etl_synthea_dbt.observation"}, {"status": "success", "timing": [{"name": "compile", "started_at": "2023-09-25T13:11:58.101023Z", "completed_at": "2023-09-25T13:11:58.104295Z"}, {"name": "execute", "started_at": "2023-09-25T13:11:58.104624Z", "completed_at": "2023-09-25T13:11:58.265864Z"}], "thread_id": "Thread-1 (worker)", "execution_time": 0.1725330352783203, "adapter_response": {"_message": "OK"}, "message": "OK", "failures": null, "unique_id": "model.etl_synthea_dbt.procedure_occurrence"}, {"status": "success", "timing": [{"name": "compile", "started_at": "2023-09-25T13:11:58.275007Z", "completed_at": "2023-09-25T13:11:58.276956Z"}, {"name": "execute", "started_at": "2023-09-25T13:11:58.277300Z", "completed_at": "2023-09-25T13:11:58.293279Z"}], "thread_id": "Thread-1 (worker)", "execution_time": 0.02390599250793457, "adapter_response": {"_message": "OK"}, "message": "OK", "failures": null, "unique_id": "model.etl_synthea_dbt.stg_condition_occurrence"}, {"status": "success", "timing": [{"name": "compile", "started_at": "2023-09-25T13:11:58.300226Z", "completed_at": "2023-09-25T13:11:58.302826Z"}, {"name": "execute", "started_at": "2023-09-25T13:11:58.303194Z", "completed_at": "2023-09-25T13:11:58.551270Z"}], "thread_id": "Thread-1 (worker)", "execution_time": 0.2933340072631836, "adapter_response": {"_message": "OK"}, "message": "OK", "failures": null, "unique_id": "model.etl_synthea_dbt.visit_detail"}, {"status": "success", "timing": [{"name": "compile", "started_at": "2023-09-25T13:11:58.595062Z", "completed_at": "2023-09-25T13:11:58.598357Z"}, {"name": "execute", "started_at": "2023-09-25T13:11:58.598789Z", "completed_at": "2023-09-25T13:12:09.697895Z"}], "thread_id": "Thread-1 (worker)", "execution_time": 11.142839193344116, "adapter_response": {"_message": "OK"}, "message": "OK", "failures": null, "unique_id": "model.etl_synthea_dbt.visit_occurrence"}, {"status": "pass", "timing": [{"name": "compile", "started_at": "2023-09-25T13:12:09.740054Z", "completed_at": "2023-09-25T13:12:09.742529Z"}, {"name": "execute", "started_at": "2023-09-25T13:12:09.742925Z", "completed_at": "2023-09-25T13:12:09.750614Z"}], "thread_id": "Thread-1 (worker)", "execution_time": 0.013612985610961914, "adapter_response": {"_message": "OK"}, "message": null, "failures": 0, "unique_id": "test.etl_synthea_dbt.not_null_observation_period_observation_period_end_date.e74764a048"}, {"status": "pass", "timing": [{"name": "compile", "started_at": "2023-09-25T13:12:09.754394Z", "completed_at": "2023-09-25T13:12:09.757123Z"}, {"name": "execute", "started_at": "2023-09-25T13:12:09.757510Z", "completed_at": "2023-09-25T13:12:09.764970Z"}], "thread_id": "Thread-1 (worker)", "execution_time": 0.01309967041015625, "adapter_response": {"_message": "OK"}, "message": null, "failures": 0, "unique_id": "test.etl_synthea_dbt.not_null_observation_period_observation_period_id.6c6fb96d33"}, {"status": "pass", "timing": [{"name": "compile", "started_at": "2023-09-25T13:12:09.768423Z", "completed_at": "2023-09-25T13:12:09.771095Z"}, {"name": "execute", "started_at": "2023-09-25T13:12:09.771601Z", "completed_at": "2023-09-25T13:12:09.781650Z"}], "thread_id": "Thread-1 (worker)", "execution_time": 0.015984773635864258, "adapter_response": {"_message": "OK"}, "message": null, "failures": 0, "unique_id": "test.etl_synthea_dbt.not_null_observation_period_observation_period_start_date.e88435db95"}, {"status": "pass", "timing": [{"name": "compile", "started_at": "2023-09-25T13:12:09.785318Z", "completed_at": "2023-09-25T13:12:09.787811Z"}, {"name": "execute", "started_at": "2023-09-25T13:12:09.788156Z", "completed_at": "2023-09-25T13:12:09.795986Z"}], "thread_id": "Thread-1 (worker)", "execution_time": 0.013148069381713867, "adapter_response": {"_message": "OK"}, "message": null, "failures": 0, "unique_id": "test.etl_synthea_dbt.not_null_observation_period_period_type_concept_id.b993e0023c"}, {"status": "pass", "timing": [{"name": "compile", "started_at": "2023-09-25T13:12:09.799441Z", "completed_at": "2023-09-25T13:12:09.802090Z"}, {"name": "execute", "started_at": "2023-09-25T13:12:09.802438Z", "completed_at": "2023-09-25T13:12:09.810997Z"}], "thread_id": "Thread-1 (worker)", "execution_time": 0.01402902603149414, "adapter_response": {"_message": "OK"}, "message": null, "failures": 0, "unique_id": "test.etl_synthea_dbt.not_null_observation_period_person_id.71c8f248d3"}, {"status": "pass", "timing": [{"name": "compile", "started_at": "2023-09-25T13:12:09.814679Z", "completed_at": "2023-09-25T13:12:09.817767Z"}, {"name": "execute", "started_at": "2023-09-25T13:12:09.818162Z", "completed_at": "2023-09-25T13:12:09.827668Z"}], "thread_id": "Thread-1 (worker)", "execution_time": 0.015707969665527344, "adapter_response": {"_message": "OK"}, "message": null, "failures": 0, "unique_id": "test.etl_synthea_dbt.relationships_observation_period_period_type_concept_id__concept_id__source_vocab_concept_.d636ade84f"}, {"status": "pass", "timing": [{"name": "compile", "started_at": "2023-09-25T13:12:09.831355Z", "completed_at": "2023-09-25T13:12:09.834852Z"}, {"name": "execute", "started_at": "2023-09-25T13:12:09.835234Z", "completed_at": "2023-09-25T13:12:09.844526Z"}], "thread_id": "Thread-1 (worker)", "execution_time": 0.015793800354003906, "adapter_response": {"_message": "OK"}, "message": null, "failures": 0, "unique_id": "test.etl_synthea_dbt.relationships_observation_period_person_id__person_id__ref_person_.3e962f56b4"}, {"status": "pass", "timing": [{"name": "compile", "started_at": "2023-09-25T13:12:09.848325Z", "completed_at": "2023-09-25T13:12:09.850832Z"}, {"name": "execute", "started_at": "2023-09-25T13:12:09.851202Z", "completed_at": "2023-09-25T13:12:09.858598Z"}], "thread_id": "Thread-1 (worker)", "execution_time": 0.012796163558959961, "adapter_response": {"_message": "OK"}, "message": null, "failures": 0, "unique_id": "test.etl_synthea_dbt.unique_observation_period_observation_period_id.34c08aa0cd"}, {"status": "pass", "timing": [{"name": "compile", "started_at": "2023-09-25T13:12:09.861962Z", "completed_at": "2023-09-25T13:12:09.864320Z"}, {"name": "execute", "started_at": "2023-09-25T13:12:09.864667Z", "completed_at": "2023-09-25T13:12:09.871871Z"}], "thread_id": "Thread-1 (worker)", "execution_time": 0.012276887893676758, "adapter_response": {"_message": "OK"}, "message": null, "failures": 0, "unique_id": "test.etl_synthea_dbt.not_null_device_exposure_device_concept_id.041c422e55"}, {"status": "pass", "timing": [{"name": "compile", "started_at": "2023-09-25T13:12:09.875511Z", "completed_at": "2023-09-25T13:12:09.878005Z"}, {"name": "execute", "started_at": "2023-09-25T13:12:09.878355Z", "completed_at": "2023-09-25T13:12:09.888126Z"}], "thread_id": "Thread-1 (worker)", "execution_time": 0.015273094177246094, "adapter_response": {"_message": "OK"}, "message": null, "failures": 0, "unique_id": "test.etl_synthea_dbt.not_null_device_exposure_device_exposure_id.ab1d5a2fe5"}, {"status": "pass", "timing": [{"name": "compile", "started_at": "2023-09-25T13:12:09.891852Z", "completed_at": "2023-09-25T13:12:09.894291Z"}, {"name": "execute", "started_at": "2023-09-25T13:12:09.894641Z", "completed_at": "2023-09-25T13:12:09.902847Z"}], "thread_id": "Thread-1 (worker)", "execution_time": 0.0135040283203125, "adapter_response": {"_message": "OK"}, "message": null, "failures": 0, "unique_id": "test.etl_synthea_dbt.not_null_device_exposure_device_exposure_start_date.23aa3e8aea"}, {"status": "pass", "timing": [{"name": "compile", "started_at": "2023-09-25T13:12:09.906270Z", "completed_at": "2023-09-25T13:12:09.908771Z"}, {"name": "execute", "started_at": "2023-09-25T13:12:09.909170Z", "completed_at": "2023-09-25T13:12:09.917973Z"}], "thread_id": "Thread-1 (worker)", "execution_time": 0.014278888702392578, "adapter_response": {"_message": "OK"}, "message": null, "failures": 0, "unique_id": "test.etl_synthea_dbt.not_null_device_exposure_device_type_concept_id.9600b2592d"}, {"status": "pass", "timing": [{"name": "compile", "started_at": "2023-09-25T13:12:09.921608Z", "completed_at": "2023-09-25T13:12:09.924122Z"}, {"name": "execute", "started_at": "2023-09-25T13:12:09.924480Z", "completed_at": "2023-09-25T13:12:09.932700Z"}], "thread_id": "Thread-1 (worker)", "execution_time": 0.013721227645874023, "adapter_response": {"_message": "OK"}, "message": null, "failures": 0, "unique_id": "test.etl_synthea_dbt.not_null_device_exposure_person_id.1330a61d39"}, {"status": "pass", "timing": [{"name": "compile", "started_at": "2023-09-25T13:12:09.936351Z", "completed_at": "2023-09-25T13:12:09.939160Z"}, {"name": "execute", "started_at": "2023-09-25T13:12:09.939537Z", "completed_at": "2023-09-25T13:12:09.948578Z"}], "thread_id": "Thread-1 (worker)", "execution_time": 0.014792919158935547, "adapter_response": {"_message": "OK"}, "message": null, "failures": 0, "unique_id": "test.etl_synthea_dbt.relationships_device_exposure_device_concept_id__concept_id__source_vocab_concept_.2545c0bdf6"}, {"status": "pass", "timing": [{"name": "compile", "started_at": "2023-09-25T13:12:09.952278Z", "completed_at": "2023-09-25T13:12:09.955194Z"}, {"name": "execute", "started_at": "2023-09-25T13:12:09.955575Z", "completed_at": "2023-09-25T13:12:09.963366Z"}], "thread_id": "Thread-1 (worker)", "execution_time": 0.013635873794555664, "adapter_response": {"_message": "OK"}, "message": null, "failures": 0, "unique_id": "test.etl_synthea_dbt.relationships_device_exposure_device_source_concept_id__concept_id__source_vocab_concept_.d5577dca4c"}, {"status": "pass", "timing": [{"name": "compile", "started_at": "2023-09-25T13:12:09.966928Z", "completed_at": "2023-09-25T13:12:09.969966Z"}, {"name": "execute", "started_at": "2023-09-25T13:12:09.970328Z", "completed_at": "2023-09-25T13:12:09.978856Z"}], "thread_id": "Thread-1 (worker)", "execution_time": 0.014295101165771484, "adapter_response": {"_message": "OK"}, "message": null, "failures": 0, "unique_id": "test.etl_synthea_dbt.relationships_device_exposure_device_type_concept_id__concept_id__source_vocab_concept_.e48c3d4798"}, {"status": "pass", "timing": [{"name": "compile", "started_at": "2023-09-25T13:12:09.982267Z", "completed_at": "2023-09-25T13:12:09.986499Z"}, {"name": "execute", "started_at": "2023-09-25T13:12:09.986874Z", "completed_at": "2023-09-25T13:12:09.995812Z"}], "thread_id": "Thread-1 (worker)", "execution_time": 0.016134023666381836, "adapter_response": {"_message": "OK"}, "message": null, "failures": 0, "unique_id": "test.etl_synthea_dbt.relationships_device_exposure_person_id__person_id__ref_person_.894d3b47b9"}, {"status": "pass", "timing": [{"name": "compile", "started_at": "2023-09-25T13:12:09.999510Z", "completed_at": "2023-09-25T13:12:10.002640Z"}, {"name": "execute", "started_at": "2023-09-25T13:12:10.003010Z", "completed_at": "2023-09-25T13:12:10.011627Z"}], "thread_id": "Thread-1 (worker)", "execution_time": 0.014652013778686523, "adapter_response": {"_message": "OK"}, "message": null, "failures": 0, "unique_id": "test.etl_synthea_dbt.relationships_device_exposure_provider_id__provider_id__ref_provider_.23736ac216"}, {"status": "pass", "timing": [{"name": "compile", "started_at": "2023-09-25T13:12:10.015244Z", "completed_at": "2023-09-25T13:12:10.018163Z"}, {"name": "execute", "started_at": "2023-09-25T13:12:10.018521Z", "completed_at": "2023-09-25T13:12:10.027136Z"}], "thread_id": "Thread-1 (worker)", "execution_time": 0.014561891555786133, "adapter_response": {"_message": "OK"}, "message": null, "failures": 0, "unique_id": "test.etl_synthea_dbt.relationships_device_exposure_unit_concept_id__concept_id__source_vocab_concept_.f445d0b9dd"}, {"status": "pass", "timing": [{"name": "compile", "started_at": "2023-09-25T13:12:10.030508Z", "completed_at": "2023-09-25T13:12:10.033695Z"}, {"name": "execute", "started_at": "2023-09-25T13:12:10.034075Z", "completed_at": "2023-09-25T13:12:10.042027Z"}], "thread_id": "Thread-1 (worker)", "execution_time": 0.01421499252319336, "adapter_response": {"_message": "OK"}, "message": null, "failures": 0, "unique_id": "test.etl_synthea_dbt.relationships_device_exposure_unit_source_concept_id__concept_id__source_vocab_concept_.75df4b5f9f"}, {"status": "pass", "timing": [{"name": "compile", "started_at": "2023-09-25T13:12:10.045641Z", "completed_at": "2023-09-25T13:12:10.048050Z"}, {"name": "execute", "started_at": "2023-09-25T13:12:10.048454Z", "completed_at": "2023-09-25T13:12:10.057433Z"}], "thread_id": "Thread-1 (worker)", "execution_time": 0.014252901077270508, "adapter_response": {"_message": "OK"}, "message": null, "failures": 0, "unique_id": "test.etl_synthea_dbt.unique_device_exposure_device_exposure_id.cdcba3488d"}, {"status": "pass", "timing": [{"name": "compile", "started_at": "2023-09-25T13:12:10.060992Z", "completed_at": "2023-09-25T13:12:10.063244Z"}, {"name": "execute", "started_at": "2023-09-25T13:12:10.063581Z", "completed_at": "2023-09-25T13:12:10.072007Z"}], "thread_id": "Thread-1 (worker)", "execution_time": 0.01353907585144043, "adapter_response": {"_message": "OK"}, "message": null, "failures": 0, "unique_id": "test.etl_synthea_dbt.not_null_drug_exposure_drug_concept_id.f309abd476"}, {"status": "pass", "timing": [{"name": "compile", "started_at": "2023-09-25T13:12:10.075655Z", "completed_at": "2023-09-25T13:12:10.078145Z"}, {"name": "execute", "started_at": "2023-09-25T13:12:10.078498Z", "completed_at": "2023-09-25T13:12:10.086576Z"}], "thread_id": "Thread-1 (worker)", "execution_time": 0.013406991958618164, "adapter_response": {"_message": "OK"}, "message": null, "failures": 0, "unique_id": "test.etl_synthea_dbt.not_null_drug_exposure_drug_exposure_end_date.89e020fdd4"}, {"status": "pass", "timing": [{"name": "compile", "started_at": "2023-09-25T13:12:10.090148Z", "completed_at": "2023-09-25T13:12:10.093882Z"}, {"name": "execute", "started_at": "2023-09-25T13:12:10.094264Z", "completed_at": "2023-09-25T13:12:10.102547Z"}], "thread_id": "Thread-1 (worker)", "execution_time": 0.015007972717285156, "adapter_response": {"_message": "OK"}, "message": null, "failures": 0, "unique_id": "test.etl_synthea_dbt.not_null_drug_exposure_drug_exposure_id.a57f0904e3"}, {"status": "pass", "timing": [{"name": "compile", "started_at": "2023-09-25T13:12:10.106139Z", "completed_at": "2023-09-25T13:12:10.108674Z"}, {"name": "execute", "started_at": "2023-09-25T13:12:10.109046Z", "completed_at": "2023-09-25T13:12:10.116887Z"}], "thread_id": "Thread-1 (worker)", "execution_time": 0.013540983200073242, "adapter_response": {"_message": "OK"}, "message": null, "failures": 0, "unique_id": "test.etl_synthea_dbt.not_null_drug_exposure_drug_exposure_start_date.61d182cfaa"}, {"status": "pass", "timing": [{"name": "compile", "started_at": "2023-09-25T13:12:10.120526Z", "completed_at": "2023-09-25T13:12:10.122966Z"}, {"name": "execute", "started_at": "2023-09-25T13:12:10.123518Z", "completed_at": "2023-09-25T13:12:10.132125Z"}], "thread_id": "Thread-1 (worker)", "execution_time": 0.014187097549438477, "adapter_response": {"_message": "OK"}, "message": null, "failures": 0, "unique_id": "test.etl_synthea_dbt.not_null_drug_exposure_drug_type_concept_id.5e130283b2"}, {"status": "pass", "timing": [{"name": "compile", "started_at": "2023-09-25T13:12:10.135883Z", "completed_at": "2023-09-25T13:12:10.138268Z"}, {"name": "execute", "started_at": "2023-09-25T13:12:10.138630Z", "completed_at": "2023-09-25T13:12:10.146822Z"}], "thread_id": "Thread-1 (worker)", "execution_time": 0.01345205307006836, "adapter_response": {"_message": "OK"}, "message": null, "failures": 0, "unique_id": "test.etl_synthea_dbt.not_null_drug_exposure_person_id.e6d75aa2b9"}, {"status": "pass", "timing": [{"name": "compile", "started_at": "2023-09-25T13:12:10.150441Z", "completed_at": "2023-09-25T13:12:10.153525Z"}, {"name": "execute", "started_at": "2023-09-25T13:12:10.153909Z", "completed_at": "2023-09-25T13:12:10.162718Z"}], "thread_id": "Thread-1 (worker)", "execution_time": 0.014935970306396484, "adapter_response": {"_message": "OK"}, "message": null, "failures": 0, "unique_id": "test.etl_synthea_dbt.relationships_drug_exposure_drug_concept_id__concept_id__source_vocab_concept_.e3645bdcef"}, {"status": "pass", "timing": [{"name": "compile", "started_at": "2023-09-25T13:12:10.166577Z", "completed_at": "2023-09-25T13:12:10.169675Z"}, {"name": "execute", "started_at": "2023-09-25T13:12:10.170046Z", "completed_at": "2023-09-25T13:12:10.178733Z"}], "thread_id": "Thread-1 (worker)", "execution_time": 0.014640092849731445, "adapter_response": {"_message": "OK"}, "message": null, "failures": 0, "unique_id": "test.etl_synthea_dbt.relationships_drug_exposure_drug_source_concept_id__concept_id__source_vocab_concept_.7dff7fc1d2"}, {"status": "pass", "timing": [{"name": "compile", "started_at": "2023-09-25T13:12:10.182312Z", "completed_at": "2023-09-25T13:12:10.185206Z"}, {"name": "execute", "started_at": "2023-09-25T13:12:10.185567Z", "completed_at": "2023-09-25T13:12:10.195325Z"}], "thread_id": "Thread-1 (worker)", "execution_time": 0.015636920928955078, "adapter_response": {"_message": "OK"}, "message": null, "failures": 0, "unique_id": "test.etl_synthea_dbt.relationships_drug_exposure_drug_type_concept_id__concept_id__source_vocab_concept_.e775235ffd"}, {"status": "pass", "timing": [{"name": "compile", "started_at": "2023-09-25T13:12:10.199068Z", "completed_at": "2023-09-25T13:12:10.201855Z"}, {"name": "execute", "started_at": "2023-09-25T13:12:10.202222Z", "completed_at": "2023-09-25T13:12:10.210982Z"}], "thread_id": "Thread-1 (worker)", "execution_time": 0.01452779769897461, "adapter_response": {"_message": "OK"}, "message": null, "failures": 0, "unique_id": "test.etl_synthea_dbt.relationships_drug_exposure_person_id__person_id__ref_person_.811ae7ceb8"}, {"status": "pass", "timing": [{"name": "compile", "started_at": "2023-09-25T13:12:10.214659Z", "completed_at": "2023-09-25T13:12:10.217719Z"}, {"name": "execute", "started_at": "2023-09-25T13:12:10.218100Z", "completed_at": "2023-09-25T13:12:10.225948Z"}], "thread_id": "Thread-1 (worker)", "execution_time": 0.013957738876342773, "adapter_response": {"_message": "OK"}, "message": null, "failures": 0, "unique_id": "test.etl_synthea_dbt.relationships_drug_exposure_provider_id__provider_id__ref_provider_.022f932272"}, {"status": "pass", "timing": [{"name": "compile", "started_at": "2023-09-25T13:12:10.229350Z", "completed_at": "2023-09-25T13:12:10.232445Z"}, {"name": "execute", "started_at": "2023-09-25T13:12:10.232869Z", "completed_at": "2023-09-25T13:12:10.241560Z"}], "thread_id": "Thread-1 (worker)", "execution_time": 0.014881134033203125, "adapter_response": {"_message": "OK"}, "message": null, "failures": 0, "unique_id": "test.etl_synthea_dbt.relationships_drug_exposure_route_concept_id__concept_id__source_vocab_concept_.67158eaf74"}, {"status": "pass", "timing": [{"name": "compile", "started_at": "2023-09-25T13:12:10.245420Z", "completed_at": "2023-09-25T13:12:10.247871Z"}, {"name": "execute", "started_at": "2023-09-25T13:12:10.248270Z", "completed_at": "2023-09-25T13:12:10.256721Z"}], "thread_id": "Thread-1 (worker)", "execution_time": 0.014068126678466797, "adapter_response": {"_message": "OK"}, "message": null, "failures": 0, "unique_id": "test.etl_synthea_dbt.unique_drug_exposure_drug_exposure_id.6e11199bfc"}, {"status": "pass", "timing": [{"name": "compile", "started_at": "2023-09-25T13:12:10.260548Z", "completed_at": "2023-09-25T13:12:10.262958Z"}, {"name": "execute", "started_at": "2023-09-25T13:12:10.263324Z", "completed_at": "2023-09-25T13:12:10.271299Z"}], "thread_id": "Thread-1 (worker)", "execution_time": 0.013036966323852539, "adapter_response": {"_message": "OK"}, "message": null, "failures": 0, "unique_id": "test.etl_synthea_dbt.not_null_measurement_measurement_concept_id.d63d0b284a"}, {"status": "pass", "timing": [{"name": "compile", "started_at": "2023-09-25T13:12:10.274680Z", "completed_at": "2023-09-25T13:12:10.277364Z"}, {"name": "execute", "started_at": "2023-09-25T13:12:10.277725Z", "completed_at": "2023-09-25T13:12:10.285575Z"}], "thread_id": "Thread-1 (worker)", "execution_time": 0.013414144515991211, "adapter_response": {"_message": "OK"}, "message": null, "failures": 0, "unique_id": "test.etl_synthea_dbt.not_null_measurement_measurement_date.f0992e3082"}, {"status": "pass", "timing": [{"name": "compile", "started_at": "2023-09-25T13:12:10.289145Z", "completed_at": "2023-09-25T13:12:10.291828Z"}, {"name": "execute", "started_at": "2023-09-25T13:12:10.292205Z", "completed_at": "2023-09-25T13:12:10.302021Z"}], "thread_id": "Thread-1 (worker)", "execution_time": 0.01526498794555664, "adapter_response": {"_message": "OK"}, "message": null, "failures": 0, "unique_id": "test.etl_synthea_dbt.not_null_measurement_measurement_id.80b56c4597"}, {"status": "pass", "timing": [{"name": "compile", "started_at": "2023-09-25T13:12:10.305286Z", "completed_at": "2023-09-25T13:12:10.308033Z"}, {"name": "execute", "started_at": "2023-09-25T13:12:10.308387Z", "completed_at": "2023-09-25T13:12:10.316562Z"}], "thread_id": "Thread-1 (worker)", "execution_time": 0.013765811920166016, "adapter_response": {"_message": "OK"}, "message": null, "failures": 0, "unique_id": "test.etl_synthea_dbt.not_null_measurement_measurement_type_concept_id.d32d33e40c"}, {"status": "pass", "timing": [{"name": "compile", "started_at": "2023-09-25T13:12:10.320136Z", "completed_at": "2023-09-25T13:12:10.322732Z"}, {"name": "execute", "started_at": "2023-09-25T13:12:10.323083Z", "completed_at": "2023-09-25T13:12:10.331120Z"}], "thread_id": "Thread-1 (worker)", "execution_time": 0.013709068298339844, "adapter_response": {"_message": "OK"}, "message": null, "failures": 0, "unique_id": "test.etl_synthea_dbt.not_null_measurement_person_id.7cf48be66f"}, {"status": "pass", "timing": [{"name": "compile", "started_at": "2023-09-25T13:12:10.334874Z", "completed_at": "2023-09-25T13:12:10.337615Z"}, {"name": "execute", "started_at": "2023-09-25T13:12:10.338053Z", "completed_at": "2023-09-25T13:12:10.346752Z"}], "thread_id": "Thread-1 (worker)", "execution_time": 0.014435768127441406, "adapter_response": {"_message": "OK"}, "message": null, "failures": 0, "unique_id": "test.etl_synthea_dbt.relationships_measurement_measurement_concept_id__concept_id__source_vocab_concept_.0fc77178f1"}, {"status": "pass", "timing": [{"name": "compile", "started_at": "2023-09-25T13:12:10.350343Z", "completed_at": "2023-09-25T13:12:10.353345Z"}, {"name": "execute", "started_at": "2023-09-25T13:12:10.353716Z", "completed_at": "2023-09-25T13:12:10.362378Z"}], "thread_id": "Thread-1 (worker)", "execution_time": 0.014577865600585938, "adapter_response": {"_message": "OK"}, "message": null, "failures": 0, "unique_id": "test.etl_synthea_dbt.relationships_measurement_measurement_source_concept_id__concept_id__source_vocab_concept_.438766d6d3"}, {"status": "pass", "timing": [{"name": "compile", "started_at": "2023-09-25T13:12:10.366039Z", "completed_at": "2023-09-25T13:12:10.368829Z"}, {"name": "execute", "started_at": "2023-09-25T13:12:10.369184Z", "completed_at": "2023-09-25T13:12:10.377063Z"}], "thread_id": "Thread-1 (worker)", "execution_time": 0.014306068420410156, "adapter_response": {"_message": "OK"}, "message": null, "failures": 0, "unique_id": "test.etl_synthea_dbt.relationships_measurement_measurement_type_concept_id__concept_id__source_vocab_concept_.05f3b90252"}, {"status": "pass", "timing": [{"name": "compile", "started_at": "2023-09-25T13:12:10.381400Z", "completed_at": "2023-09-25T13:12:10.384398Z"}, {"name": "execute", "started_at": "2023-09-25T13:12:10.384778Z", "completed_at": "2023-09-25T13:12:10.393757Z"}], "thread_id": "Thread-1 (worker)", "execution_time": 0.015552997589111328, "adapter_response": {"_message": "OK"}, "message": null, "failures": 0, "unique_id": "test.etl_synthea_dbt.relationships_measurement_operator_concept_id__concept_id__source_vocab_concept_.fd5f030894"}, {"status": "pass", "timing": [{"name": "compile", "started_at": "2023-09-25T13:12:10.397795Z", "completed_at": "2023-09-25T13:12:10.401816Z"}, {"name": "execute", "started_at": "2023-09-25T13:12:10.402177Z", "completed_at": "2023-09-25T13:12:10.410643Z"}], "thread_id": "Thread-1 (worker)", "execution_time": 0.015403985977172852, "adapter_response": {"_message": "OK"}, "message": null, "failures": 0, "unique_id": "test.etl_synthea_dbt.relationships_measurement_person_id__person_id__ref_person_.b9201b5f92"}, {"status": "pass", "timing": [{"name": "compile", "started_at": "2023-09-25T13:12:10.414425Z", "completed_at": "2023-09-25T13:12:10.417328Z"}, {"name": "execute", "started_at": "2023-09-25T13:12:10.417689Z", "completed_at": "2023-09-25T13:12:10.425633Z"}], "thread_id": "Thread-1 (worker)", "execution_time": 0.014066219329833984, "adapter_response": {"_message": "OK"}, "message": null, "failures": 0, "unique_id": "test.etl_synthea_dbt.relationships_measurement_provider_id__provider_id__ref_provider_.1f264234a4"}, {"status": "pass", "timing": [{"name": "compile", "started_at": "2023-09-25T13:12:10.429352Z", "completed_at": "2023-09-25T13:12:10.432505Z"}, {"name": "execute", "started_at": "2023-09-25T13:12:10.432868Z", "completed_at": "2023-09-25T13:12:10.441226Z"}], "thread_id": "Thread-1 (worker)", "execution_time": 0.014495849609375, "adapter_response": {"_message": "OK"}, "message": null, "failures": 0, "unique_id": "test.etl_synthea_dbt.relationships_measurement_unit_concept_id__concept_id__source_vocab_concept_.ddb1f5242b"}, {"status": "pass", "timing": [{"name": "compile", "started_at": "2023-09-25T13:12:10.444997Z", "completed_at": "2023-09-25T13:12:10.448034Z"}, {"name": "execute", "started_at": "2023-09-25T13:12:10.448492Z", "completed_at": "2023-09-25T13:12:10.456400Z"}], "thread_id": "Thread-1 (worker)", "execution_time": 0.014214754104614258, "adapter_response": {"_message": "OK"}, "message": null, "failures": 0, "unique_id": "test.etl_synthea_dbt.relationships_measurement_value_as_concept_id__concept_id__source_vocab_concept_.85566490c4"}, {"status": "pass", "timing": [{"name": "compile", "started_at": "2023-09-25T13:12:10.460327Z", "completed_at": "2023-09-25T13:12:10.462629Z"}, {"name": "execute", "started_at": "2023-09-25T13:12:10.463000Z", "completed_at": "2023-09-25T13:12:10.471561Z"}], "thread_id": "Thread-1 (worker)", "execution_time": 0.01380300521850586, "adapter_response": {"_message": "OK"}, "message": null, "failures": 0, "unique_id": "test.etl_synthea_dbt.unique_measurement_measurement_id.a3f1e8466d"}, {"status": "pass", "timing": [{"name": "compile", "started_at": "2023-09-25T13:12:10.475241Z", "completed_at": "2023-09-25T13:12:10.477734Z"}, {"name": "execute", "started_at": "2023-09-25T13:12:10.478095Z", "completed_at": "2023-09-25T13:12:10.485604Z"}], "thread_id": "Thread-1 (worker)", "execution_time": 0.013059854507446289, "adapter_response": {"_message": "OK"}, "message": null, "failures": 0, "unique_id": "test.etl_synthea_dbt.not_null_observation_observation_concept_id.4725260db7"}, {"status": "pass", "timing": [{"name": "compile", "started_at": "2023-09-25T13:12:10.489376Z", "completed_at": "2023-09-25T13:12:10.491939Z"}, {"name": "execute", "started_at": "2023-09-25T13:12:10.492304Z", "completed_at": "2023-09-25T13:12:10.499853Z"}], "thread_id": "Thread-1 (worker)", "execution_time": 0.01325535774230957, "adapter_response": {"_message": "OK"}, "message": null, "failures": 0, "unique_id": "test.etl_synthea_dbt.not_null_observation_observation_date.0cde7d2dd7"}, {"status": "pass", "timing": [{"name": "compile", "started_at": "2023-09-25T13:12:10.503551Z", "completed_at": "2023-09-25T13:12:10.507098Z"}, {"name": "execute", "started_at": "2023-09-25T13:12:10.507473Z", "completed_at": "2023-09-25T13:12:10.516058Z"}], "thread_id": "Thread-1 (worker)", "execution_time": 0.015034198760986328, "adapter_response": {"_message": "OK"}, "message": null, "failures": 0, "unique_id": "test.etl_synthea_dbt.not_null_observation_observation_id.efd24835d6"}, {"status": "pass", "timing": [{"name": "compile", "started_at": "2023-09-25T13:12:10.519716Z", "completed_at": "2023-09-25T13:12:10.522105Z"}, {"name": "execute", "started_at": "2023-09-25T13:12:10.522456Z", "completed_at": "2023-09-25T13:12:10.530832Z"}], "thread_id": "Thread-1 (worker)", "execution_time": 0.013597965240478516, "adapter_response": {"_message": "OK"}, "message": null, "failures": 0, "unique_id": "test.etl_synthea_dbt.not_null_observation_observation_type_concept_id.3f8e08f159"}, {"status": "pass", "timing": [{"name": "compile", "started_at": "2023-09-25T13:12:10.534389Z", "completed_at": "2023-09-25T13:12:10.536950Z"}, {"name": "execute", "started_at": "2023-09-25T13:12:10.537297Z", "completed_at": "2023-09-25T13:12:10.545603Z"}], "thread_id": "Thread-1 (worker)", "execution_time": 0.013869047164916992, "adapter_response": {"_message": "OK"}, "message": null, "failures": 0, "unique_id": "test.etl_synthea_dbt.not_null_observation_person_id.8fa7495344"}, {"status": "pass", "timing": [{"name": "compile", "started_at": "2023-09-25T13:12:10.549383Z", "completed_at": "2023-09-25T13:12:10.552307Z"}, {"name": "execute", "started_at": "2023-09-25T13:12:10.552692Z", "completed_at": "2023-09-25T13:12:10.561381Z"}], "thread_id": "Thread-1 (worker)", "execution_time": 0.014350175857543945, "adapter_response": {"_message": "OK"}, "message": null, "failures": 0, "unique_id": "test.etl_synthea_dbt.relationships_observation_obs_event_field_concept_id__concept_id__source_vocab_concept_.1c7bfac6f6"}, {"status": "pass", "timing": [{"name": "compile", "started_at": "2023-09-25T13:12:10.564905Z", "completed_at": "2023-09-25T13:12:10.567993Z"}, {"name": "execute", "started_at": "2023-09-25T13:12:10.568360Z", "completed_at": "2023-09-25T13:12:10.576947Z"}], "thread_id": "Thread-1 (worker)", "execution_time": 0.014547109603881836, "adapter_response": {"_message": "OK"}, "message": null, "failures": 0, "unique_id": "test.etl_synthea_dbt.relationships_observation_observation_concept_id__concept_id__source_vocab_concept_.d6cdb5cd5e"}, {"status": "pass", "timing": [{"name": "compile", "started_at": "2023-09-25T13:12:10.580433Z", "completed_at": "2023-09-25T13:12:10.583675Z"}, {"name": "execute", "started_at": "2023-09-25T13:12:10.584045Z", "completed_at": "2023-09-25T13:12:10.592373Z"}], "thread_id": "Thread-1 (worker)", "execution_time": 0.014618158340454102, "adapter_response": {"_message": "OK"}, "message": null, "failures": 0, "unique_id": "test.etl_synthea_dbt.relationships_observation_observation_source_concept_id__concept_id__source_vocab_concept_.cc7ef061f3"}, {"status": "pass", "timing": [{"name": "compile", "started_at": "2023-09-25T13:12:10.595987Z", "completed_at": "2023-09-25T13:12:10.599104Z"}, {"name": "execute", "started_at": "2023-09-25T13:12:10.599510Z", "completed_at": "2023-09-25T13:12:10.609282Z"}], "thread_id": "Thread-1 (worker)", "execution_time": 0.015897035598754883, "adapter_response": {"_message": "OK"}, "message": null, "failures": 0, "unique_id": "test.etl_synthea_dbt.relationships_observation_observation_type_concept_id__concept_id__source_vocab_concept_.d6bea239d2"}, {"status": "pass", "timing": [{"name": "compile", "started_at": "2023-09-25T13:12:10.613059Z", "completed_at": "2023-09-25T13:12:10.615907Z"}, {"name": "execute", "started_at": "2023-09-25T13:12:10.616295Z", "completed_at": "2023-09-25T13:12:10.623745Z"}], "thread_id": "Thread-1 (worker)", "execution_time": 0.013274192810058594, "adapter_response": {"_message": "OK"}, "message": null, "failures": 0, "unique_id": "test.etl_synthea_dbt.relationships_observation_person_id__person_id__ref_person_.e1ae5f3106"}, {"status": "pass", "timing": [{"name": "compile", "started_at": "2023-09-25T13:12:10.627462Z", "completed_at": "2023-09-25T13:12:10.630334Z"}, {"name": "execute", "started_at": "2023-09-25T13:12:10.630707Z", "completed_at": "2023-09-25T13:12:10.638406Z"}], "thread_id": "Thread-1 (worker)", "execution_time": 0.013547897338867188, "adapter_response": {"_message": "OK"}, "message": null, "failures": 0, "unique_id": "test.etl_synthea_dbt.relationships_observation_provider_id__provider_id__ref_provider_.531e2ef5ba"}, {"status": "pass", "timing": [{"name": "compile", "started_at": "2023-09-25T13:12:10.641998Z", "completed_at": "2023-09-25T13:12:10.645048Z"}, {"name": "execute", "started_at": "2023-09-25T13:12:10.645415Z", "completed_at": "2023-09-25T13:12:10.655063Z"}], "thread_id": "Thread-1 (worker)", "execution_time": 0.015645980834960938, "adapter_response": {"_message": "OK"}, "message": null, "failures": 0, "unique_id": "test.etl_synthea_dbt.relationships_observation_qualifier_concept_id__concept_id__source_vocab_concept_.2145be4c80"}, {"status": "pass", "timing": [{"name": "compile", "started_at": "2023-09-25T13:12:10.658857Z", "completed_at": "2023-09-25T13:12:10.661943Z"}, {"name": "execute", "started_at": "2023-09-25T13:12:10.662319Z", "completed_at": "2023-09-25T13:12:10.671169Z"}], "thread_id": "Thread-1 (worker)", "execution_time": 0.014991044998168945, "adapter_response": {"_message": "OK"}, "message": null, "failures": 0, "unique_id": "test.etl_synthea_dbt.relationships_observation_unit_concept_id__concept_id__source_vocab_concept_.4d3119aedd"}, {"status": "pass", "timing": [{"name": "compile", "started_at": "2023-09-25T13:12:10.674970Z", "completed_at": "2023-09-25T13:12:10.678122Z"}, {"name": "execute", "started_at": "2023-09-25T13:12:10.678494Z", "completed_at": "2023-09-25T13:12:10.687259Z"}], "thread_id": "Thread-1 (worker)", "execution_time": 0.015037059783935547, "adapter_response": {"_message": "OK"}, "message": null, "failures": 0, "unique_id": "test.etl_synthea_dbt.relationships_observation_value_as_concept_id__concept_id__source_vocab_concept_.14ce6d5d7c"}, {"status": "pass", "timing": [{"name": "compile", "started_at": "2023-09-25T13:12:10.691170Z", "completed_at": "2023-09-25T13:12:10.693668Z"}, {"name": "execute", "started_at": "2023-09-25T13:12:10.694052Z", "completed_at": "2023-09-25T13:12:10.702659Z"}], "thread_id": "Thread-1 (worker)", "execution_time": 0.014848947525024414, "adapter_response": {"_message": "OK"}, "message": null, "failures": 0, "unique_id": "test.etl_synthea_dbt.unique_observation_observation_id.c7fcc2846f"}, {"status": "pass", "timing": [{"name": "compile", "started_at": "2023-09-25T13:12:10.707374Z", "completed_at": "2023-09-25T13:12:10.709782Z"}, {"name": "execute", "started_at": "2023-09-25T13:12:10.710121Z", "completed_at": "2023-09-25T13:12:10.719471Z"}], "thread_id": "Thread-1 (worker)", "execution_time": 0.014611244201660156, "adapter_response": {"_message": "OK"}, "message": null, "failures": 0, "unique_id": "test.etl_synthea_dbt.not_null_procedure_occurrence_person_id.95f33a8709"}, {"status": "pass", "timing": [{"name": "compile", "started_at": "2023-09-25T13:12:10.722917Z", "completed_at": "2023-09-25T13:12:10.725734Z"}, {"name": "execute", "started_at": "2023-09-25T13:12:10.726114Z", "completed_at": "2023-09-25T13:12:10.734740Z"}], "thread_id": "Thread-1 (worker)", "execution_time": 0.014446020126342773, "adapter_response": {"_message": "OK"}, "message": null, "failures": 0, "unique_id": "test.etl_synthea_dbt.not_null_procedure_occurrence_procedure_concept_id.39a7f862ab"}, {"status": "pass", "timing": [{"name": "compile", "started_at": "2023-09-25T13:12:10.738478Z", "completed_at": "2023-09-25T13:12:10.741267Z"}, {"name": "execute", "started_at": "2023-09-25T13:12:10.741667Z", "completed_at": "2023-09-25T13:12:10.750626Z"}], "thread_id": "Thread-1 (worker)", "execution_time": 0.015367746353149414, "adapter_response": {"_message": "OK"}, "message": null, "failures": 0, "unique_id": "test.etl_synthea_dbt.not_null_procedure_occurrence_procedure_date.7e26c7adde"}, {"status": "pass", "timing": [{"name": "compile", "started_at": "2023-09-25T13:12:10.755058Z", "completed_at": "2023-09-25T13:12:10.757859Z"}, {"name": "execute", "started_at": "2023-09-25T13:12:10.758273Z", "completed_at": "2023-09-25T13:12:10.766258Z"}], "thread_id": "Thread-1 (worker)", "execution_time": 0.014206886291503906, "adapter_response": {"_message": "OK"}, "message": null, "failures": 0, "unique_id": "test.etl_synthea_dbt.not_null_procedure_occurrence_procedure_occurrence_id.e3b1d90a98"}, {"status": "pass", "timing": [{"name": "compile", "started_at": "2023-09-25T13:12:10.770213Z", "completed_at": "2023-09-25T13:12:10.772984Z"}, {"name": "execute", "started_at": "2023-09-25T13:12:10.773372Z", "completed_at": "2023-09-25T13:12:10.782100Z"}], "thread_id": "Thread-1 (worker)", "execution_time": 0.014644145965576172, "adapter_response": {"_message": "OK"}, "message": null, "failures": 0, "unique_id": "test.etl_synthea_dbt.not_null_procedure_occurrence_procedure_type_concept_id.697b6199fb"}, {"status": "pass", "timing": [{"name": "compile", "started_at": "2023-09-25T13:12:10.786104Z", "completed_at": "2023-09-25T13:12:10.789333Z"}, {"name": "execute", "started_at": "2023-09-25T13:12:10.789725Z", "completed_at": "2023-09-25T13:12:10.798219Z"}], "thread_id": "Thread-1 (worker)", "execution_time": 0.014765739440917969, "adapter_response": {"_message": "OK"}, "message": null, "failures": 0, "unique_id": "test.etl_synthea_dbt.relationships_procedure_occurrence_modifier_concept_id__concept_id__source_vocab_concept_.a73220f756"}, {"status": "pass", "timing": [{"name": "compile", "started_at": "2023-09-25T13:12:10.802229Z", "completed_at": "2023-09-25T13:12:10.804957Z"}, {"name": "execute", "started_at": "2023-09-25T13:12:10.805334Z", "completed_at": "2023-09-25T13:12:10.813982Z"}], "thread_id": "Thread-1 (worker)", "execution_time": 0.014663219451904297, "adapter_response": {"_message": "OK"}, "message": null, "failures": 0, "unique_id": "test.etl_synthea_dbt.relationships_procedure_occurrence_person_id__person_id__ref_person_.901403d0b9"}, {"status": "pass", "timing": [{"name": "compile", "started_at": "2023-09-25T13:12:10.818139Z", "completed_at": "2023-09-25T13:12:10.822755Z"}, {"name": "execute", "started_at": "2023-09-25T13:12:10.823147Z", "completed_at": "2023-09-25T13:12:10.831337Z"}], "thread_id": "Thread-1 (worker)", "execution_time": 0.01602005958557129, "adapter_response": {"_message": "OK"}, "message": null, "failures": 0, "unique_id": "test.etl_synthea_dbt.relationships_procedure_occurrence_procedure_concept_id__concept_id__source_vocab_concept_.1d83da347f"}, {"status": "pass", "timing": [{"name": "compile", "started_at": "2023-09-25T13:12:10.835426Z", "completed_at": "2023-09-25T13:12:10.838013Z"}, {"name": "execute", "started_at": "2023-09-25T13:12:10.838368Z", "completed_at": "2023-09-25T13:12:10.847148Z"}], "thread_id": "Thread-1 (worker)", "execution_time": 0.014344930648803711, "adapter_response": {"_message": "OK"}, "message": null, "failures": 0, "unique_id": "test.etl_synthea_dbt.relationships_procedure_occurrence_procedure_source_concept_id__concept_id__source_vocab_concept_.9c4ee06eea"}, {"status": "pass", "timing": [{"name": "compile", "started_at": "2023-09-25T13:12:10.850978Z", "completed_at": "2023-09-25T13:12:10.854102Z"}, {"name": "execute", "started_at": "2023-09-25T13:12:10.854485Z", "completed_at": "2023-09-25T13:12:10.863636Z"}], "thread_id": "Thread-1 (worker)", "execution_time": 0.015337944030761719, "adapter_response": {"_message": "OK"}, "message": null, "failures": 0, "unique_id": "test.etl_synthea_dbt.relationships_procedure_occurrence_procedure_type_concept_id__concept_id__source_vocab_concept_.1183d8fa7c"}, {"status": "pass", "timing": [{"name": "compile", "started_at": "2023-09-25T13:12:10.867427Z", "completed_at": "2023-09-25T13:12:10.870573Z"}, {"name": "execute", "started_at": "2023-09-25T13:12:10.870967Z", "completed_at": "2023-09-25T13:12:10.879928Z"}], "thread_id": "Thread-1 (worker)", "execution_time": 0.015537261962890625, "adapter_response": {"_message": "OK"}, "message": null, "failures": 0, "unique_id": "test.etl_synthea_dbt.relationships_procedure_occurrence_provider_id__provider_id__ref_provider_.c610ac14c8"}, {"status": "pass", "timing": [{"name": "compile", "started_at": "2023-09-25T13:12:10.884050Z", "completed_at": "2023-09-25T13:12:10.886581Z"}, {"name": "execute", "started_at": "2023-09-25T13:12:10.886946Z", "completed_at": "2023-09-25T13:12:10.895746Z"}], "thread_id": "Thread-1 (worker)", "execution_time": 0.014539003372192383, "adapter_response": {"_message": "OK"}, "message": null, "failures": 0, "unique_id": "test.etl_synthea_dbt.unique_procedure_occurrence_procedure_occurrence_id.fb0663ac66"}, {"status": "success", "timing": [{"name": "compile", "started_at": "2023-09-25T13:12:10.899803Z", "completed_at": "2023-09-25T13:12:10.904296Z"}, {"name": "execute", "started_at": "2023-09-25T13:12:10.904747Z", "completed_at": "2023-09-25T13:12:11.068767Z"}], "thread_id": "Thread-1 (worker)", "execution_time": 0.17808103561401367, "adapter_response": {"_message": "OK"}, "message": "OK", "failures": null, "unique_id": "model.etl_synthea_dbt.condition_occurrence"}, {"status": "pass", "timing": [{"name": "compile", "started_at": "2023-09-25T13:12:11.079455Z", "completed_at": "2023-09-25T13:12:11.081553Z"}, {"name": "execute", "started_at": "2023-09-25T13:12:11.081912Z", "completed_at": "2023-09-25T13:12:11.088882Z"}], "thread_id": "Thread-1 (worker)", "execution_time": 0.01175689697265625, "adapter_response": {"_message": "OK"}, "message": null, "failures": 0, "unique_id": "test.etl_synthea_dbt.not_null_visit_detail_person_id.f40d29958e"}, {"status": "pass", "timing": [{"name": "compile", "started_at": "2023-09-25T13:12:11.092053Z", "completed_at": "2023-09-25T13:12:11.094614Z"}, {"name": "execute", "started_at": "2023-09-25T13:12:11.094992Z", "completed_at": "2023-09-25T13:12:11.103041Z"}], "thread_id": "Thread-1 (worker)", "execution_time": 0.013442039489746094, "adapter_response": {"_message": "OK"}, "message": null, "failures": 0, "unique_id": "test.etl_synthea_dbt.not_null_visit_detail_visit_detail_concept_id.11df83fc24"}, {"status": "pass", "timing": [{"name": "compile", "started_at": "2023-09-25T13:12:11.106462Z", "completed_at": "2023-09-25T13:12:11.109096Z"}, {"name": "execute", "started_at": "2023-09-25T13:12:11.109497Z", "completed_at": "2023-09-25T13:12:11.117246Z"}], "thread_id": "Thread-1 (worker)", "execution_time": 0.013510942459106445, "adapter_response": {"_message": "OK"}, "message": null, "failures": 0, "unique_id": "test.etl_synthea_dbt.not_null_visit_detail_visit_detail_end_date.fbf8c3e1c7"}, {"status": "pass", "timing": [{"name": "compile", "started_at": "2023-09-25T13:12:11.121088Z", "completed_at": "2023-09-25T13:12:11.123620Z"}, {"name": "execute", "started_at": "2023-09-25T13:12:11.124008Z", "completed_at": "2023-09-25T13:12:11.131252Z"}], "thread_id": "Thread-1 (worker)", "execution_time": 0.012796878814697266, "adapter_response": {"_message": "OK"}, "message": null, "failures": 0, "unique_id": "test.etl_synthea_dbt.not_null_visit_detail_visit_detail_id.e5b9e9d282"}, {"status": "pass", "timing": [{"name": "compile", "started_at": "2023-09-25T13:12:11.134934Z", "completed_at": "2023-09-25T13:12:11.137465Z"}, {"name": "execute", "started_at": "2023-09-25T13:12:11.137846Z", "completed_at": "2023-09-25T13:12:11.146061Z"}], "thread_id": "Thread-1 (worker)", "execution_time": 0.01381993293762207, "adapter_response": {"_message": "OK"}, "message": null, "failures": 0, "unique_id": "test.etl_synthea_dbt.not_null_visit_detail_visit_detail_start_date.cc3c8c51a7"}, {"status": "pass", "timing": [{"name": "compile", "started_at": "2023-09-25T13:12:11.149927Z", "completed_at": "2023-09-25T13:12:11.152624Z"}, {"name": "execute", "started_at": "2023-09-25T13:12:11.152984Z", "completed_at": "2023-09-25T13:12:11.160764Z"}], "thread_id": "Thread-1 (worker)", "execution_time": 0.01337122917175293, "adapter_response": {"_message": "OK"}, "message": null, "failures": 0, "unique_id": "test.etl_synthea_dbt.not_null_visit_detail_visit_detail_type_concept_id.31ca3f2172"}, {"status": "pass", "timing": [{"name": "compile", "started_at": "2023-09-25T13:12:11.164297Z", "completed_at": "2023-09-25T13:12:11.168894Z"}, {"name": "execute", "started_at": "2023-09-25T13:12:11.169265Z", "completed_at": "2023-09-25T13:12:11.178162Z"}], "thread_id": "Thread-1 (worker)", "execution_time": 0.016398906707763672, "adapter_response": {"_message": "OK"}, "message": null, "failures": 0, "unique_id": "test.etl_synthea_dbt.relationships_device_exposure_visit_detail_id__visit_detail_id__ref_visit_detail_.c064b67cdb"}, {"status": "pass", "timing": [{"name": "compile", "started_at": "2023-09-25T13:12:11.182009Z", "completed_at": "2023-09-25T13:12:11.184853Z"}, {"name": "execute", "started_at": "2023-09-25T13:12:11.185212Z", "completed_at": "2023-09-25T13:12:11.193805Z"}], "thread_id": "Thread-1 (worker)", "execution_time": 0.014397859573364258, "adapter_response": {"_message": "OK"}, "message": null, "failures": 0, "unique_id": "test.etl_synthea_dbt.relationships_drug_exposure_visit_detail_id__visit_detail_id__ref_visit_detail_.770b0c9b99"}, {"status": "pass", "timing": [{"name": "compile", "started_at": "2023-09-25T13:12:11.197360Z", "completed_at": "2023-09-25T13:12:11.200405Z"}, {"name": "execute", "started_at": "2023-09-25T13:12:11.200781Z", "completed_at": "2023-09-25T13:12:11.209219Z"}], "thread_id": "Thread-1 (worker)", "execution_time": 0.014470100402832031, "adapter_response": {"_message": "OK"}, "message": null, "failures": 0, "unique_id": "test.etl_synthea_dbt.relationships_measurement_visit_detail_id__visit_detail_id__ref_visit_detail_.d4200ff3e2"}, {"status": "pass", "timing": [{"name": "compile", "started_at": "2023-09-25T13:12:11.212864Z", "completed_at": "2023-09-25T13:12:11.215570Z"}, {"name": "execute", "started_at": "2023-09-25T13:12:11.215948Z", "completed_at": "2023-09-25T13:12:11.224462Z"}], "thread_id": "Thread-1 (worker)", "execution_time": 0.014226198196411133, "adapter_response": {"_message": "OK"}, "message": null, "failures": 0, "unique_id": "test.etl_synthea_dbt.relationships_observation_visit_detail_id__visit_detail_id__ref_visit_detail_.b9b6665fca"}, {"status": "pass", "timing": [{"name": "compile", "started_at": "2023-09-25T13:12:11.228161Z", "completed_at": "2023-09-25T13:12:11.231219Z"}, {"name": "execute", "started_at": "2023-09-25T13:12:11.231720Z", "completed_at": "2023-09-25T13:12:11.239473Z"}], "thread_id": "Thread-1 (worker)", "execution_time": 0.014016866683959961, "adapter_response": {"_message": "OK"}, "message": null, "failures": 0, "unique_id": "test.etl_synthea_dbt.relationships_procedure_occurrence_visit_detail_id__visit_detail_id__ref_visit_detail_.aad4bd00c4"}, {"status": "pass", "timing": [{"name": "compile", "started_at": "2023-09-25T13:12:11.243374Z", "completed_at": "2023-09-25T13:12:11.246129Z"}, {"name": "execute", "started_at": "2023-09-25T13:12:11.246618Z", "completed_at": "2023-09-25T13:12:11.284727Z"}], "thread_id": "Thread-1 (worker)", "execution_time": 0.04398798942565918, "adapter_response": {"_message": "OK"}, "message": null, "failures": 0, "unique_id": "test.etl_synthea_dbt.relationships_visit_detail_admitting_source_concept_id__concept_id__source_vocab_concept_.7433619460"}, {"status": "pass", "timing": [{"name": "compile", "started_at": "2023-09-25T13:12:11.288523Z", "completed_at": "2023-09-25T13:12:11.291366Z"}, {"name": "execute", "started_at": "2023-09-25T13:12:11.291737Z", "completed_at": "2023-09-25T13:12:11.331286Z"}], "thread_id": "Thread-1 (worker)", "execution_time": 0.04677009582519531, "adapter_response": {"_message": "OK"}, "message": null, "failures": 0, "unique_id": "test.etl_synthea_dbt.relationships_visit_detail_discharge_to_concept_id__concept_id__source_vocab_concept_.dff6013593"}, {"status": "pass", "timing": [{"name": "compile", "started_at": "2023-09-25T13:12:11.336167Z", "completed_at": "2023-09-25T13:12:11.338818Z"}, {"name": "execute", "started_at": "2023-09-25T13:12:11.339173Z", "completed_at": "2023-09-25T13:12:11.347221Z"}], "thread_id": "Thread-1 (worker)", "execution_time": 0.013521909713745117, "adapter_response": {"_message": "OK"}, "message": null, "failures": 0, "unique_id": "test.etl_synthea_dbt.relationships_visit_detail_parent_visit_detail_id__visit_detail_id__ref_visit_detail_.3f45535d08"}, {"status": "pass", "timing": [{"name": "compile", "started_at": "2023-09-25T13:12:11.350677Z", "completed_at": "2023-09-25T13:12:11.353518Z"}, {"name": "execute", "started_at": "2023-09-25T13:12:11.353875Z", "completed_at": "2023-09-25T13:12:11.363288Z"}], "thread_id": "Thread-1 (worker)", "execution_time": 0.01501321792602539, "adapter_response": {"_message": "OK"}, "message": null, "failures": 0, "unique_id": "test.etl_synthea_dbt.relationships_visit_detail_person_id__person_id__ref_person_.a572cd3588"}, {"status": "pass", "timing": [{"name": "compile", "started_at": "2023-09-25T13:12:11.366718Z", "completed_at": "2023-09-25T13:12:11.369611Z"}, {"name": "execute", "started_at": "2023-09-25T13:12:11.370002Z", "completed_at": "2023-09-25T13:12:11.380496Z"}], "thread_id": "Thread-1 (worker)", "execution_time": 0.017163991928100586, "adapter_response": {"_message": "OK"}, "message": null, "failures": 0, "unique_id": "test.etl_synthea_dbt.relationships_visit_detail_preceding_visit_detail_id__visit_detail_id__ref_visit_detail_.c17ffa5654"}, {"status": "pass", "timing": [{"name": "compile", "started_at": "2023-09-25T13:12:11.384949Z", "completed_at": "2023-09-25T13:12:11.387692Z"}, {"name": "execute", "started_at": "2023-09-25T13:12:11.388057Z", "completed_at": "2023-09-25T13:12:11.396803Z"}], "thread_id": "Thread-1 (worker)", "execution_time": 0.01540684700012207, "adapter_response": {"_message": "OK"}, "message": null, "failures": 0, "unique_id": "test.etl_synthea_dbt.relationships_visit_detail_provider_id__provider_id__ref_provider_.7393623c5e"}, {"status": "pass", "timing": [{"name": "compile", "started_at": "2023-09-25T13:12:11.401538Z", "completed_at": "2023-09-25T13:12:11.404495Z"}, {"name": "execute", "started_at": "2023-09-25T13:12:11.404873Z", "completed_at": "2023-09-25T13:12:11.442350Z"}], "thread_id": "Thread-1 (worker)", "execution_time": 0.044243812561035156, "adapter_response": {"_message": "OK"}, "message": null, "failures": 0, "unique_id": "test.etl_synthea_dbt.relationships_visit_detail_visit_detail_concept_id__concept_id__source_vocab_concept_.f6539e5bad"}, {"status": "pass", "timing": [{"name": "compile", "started_at": "2023-09-25T13:12:11.446793Z", "completed_at": "2023-09-25T13:12:11.449452Z"}, {"name": "execute", "started_at": "2023-09-25T13:12:11.449822Z", "completed_at": "2023-09-25T13:12:11.487773Z"}], "thread_id": "Thread-1 (worker)", "execution_time": 0.044790029525756836, "adapter_response": {"_message": "OK"}, "message": null, "failures": 0, "unique_id": "test.etl_synthea_dbt.relationships_visit_detail_visit_detail_source_concept_id__concept_id__source_vocab_concept_.90e855b8ea"}, {"status": "pass", "timing": [{"name": "compile", "started_at": "2023-09-25T13:12:11.492544Z", "completed_at": "2023-09-25T13:12:11.495421Z"}, {"name": "execute", "started_at": "2023-09-25T13:12:11.495817Z", "completed_at": "2023-09-25T13:12:11.534940Z"}], "thread_id": "Thread-1 (worker)", "execution_time": 0.04504084587097168, "adapter_response": {"_message": "OK"}, "message": null, "failures": 0, "unique_id": "test.etl_synthea_dbt.relationships_visit_detail_visit_detail_type_concept_id__concept_id__source_vocab_concept_.0564ecbaa6"}, {"status": "pass", "timing": [{"name": "compile", "started_at": "2023-09-25T13:12:11.538343Z", "completed_at": "2023-09-25T13:12:11.540526Z"}, {"name": "execute", "started_at": "2023-09-25T13:12:11.540853Z", "completed_at": "2023-09-25T13:12:11.553605Z"}], "thread_id": "Thread-1 (worker)", "execution_time": 0.017655134201049805, "adapter_response": {"_message": "OK"}, "message": null, "failures": 0, "unique_id": "test.etl_synthea_dbt.unique_visit_detail_visit_detail_id.1f90f95601"}, {"status": "pass", "timing": [{"name": "compile", "started_at": "2023-09-25T13:12:11.557144Z", "completed_at": "2023-09-25T13:12:11.559498Z"}, {"name": "execute", "started_at": "2023-09-25T13:12:11.559869Z", "completed_at": "2023-09-25T13:12:11.569086Z"}], "thread_id": "Thread-1 (worker)", "execution_time": 0.015146970748901367, "adapter_response": {"_message": "OK"}, "message": null, "failures": 0, "unique_id": "test.etl_synthea_dbt.not_null_visit_occurrence_person_id.e916ff163a"}, {"status": "pass", "timing": [{"name": "compile", "started_at": "2023-09-25T13:12:11.573538Z", "completed_at": "2023-09-25T13:12:11.576074Z"}, {"name": "execute", "started_at": "2023-09-25T13:12:11.576419Z", "completed_at": "2023-09-25T13:12:11.583529Z"}], "thread_id": "Thread-1 (worker)", "execution_time": 0.012652158737182617, "adapter_response": {"_message": "OK"}, "message": null, "failures": 0, "unique_id": "test.etl_synthea_dbt.not_null_visit_occurrence_visit_concept_id.e13dd76157"}, {"status": "pass", "timing": [{"name": "compile", "started_at": "2023-09-25T13:12:11.586980Z", "completed_at": "2023-09-25T13:12:11.589405Z"}, {"name": "execute", "started_at": "2023-09-25T13:12:11.589853Z", "completed_at": "2023-09-25T13:12:11.598306Z"}], "thread_id": "Thread-1 (worker)", "execution_time": 0.014044046401977539, "adapter_response": {"_message": "OK"}, "message": null, "failures": 0, "unique_id": "test.etl_synthea_dbt.not_null_visit_occurrence_visit_end_date.47f6967fe8"}, {"status": "pass", "timing": [{"name": "compile", "started_at": "2023-09-25T13:12:11.602197Z", "completed_at": "2023-09-25T13:12:11.604563Z"}, {"name": "execute", "started_at": "2023-09-25T13:12:11.604933Z", "completed_at": "2023-09-25T13:12:11.613256Z"}], "thread_id": "Thread-1 (worker)", "execution_time": 0.013711214065551758, "adapter_response": {"_message": "OK"}, "message": null, "failures": 0, "unique_id": "test.etl_synthea_dbt.not_null_visit_occurrence_visit_occurrence_id.a3a65446cf"}, {"status": "pass", "timing": [{"name": "compile", "started_at": "2023-09-25T13:12:11.617022Z", "completed_at": "2023-09-25T13:12:11.619502Z"}, {"name": "execute", "started_at": "2023-09-25T13:12:11.619859Z", "completed_at": "2023-09-25T13:12:11.627916Z"}], "thread_id": "Thread-1 (worker)", "execution_time": 0.013406991958618164, "adapter_response": {"_message": "OK"}, "message": null, "failures": 0, "unique_id": "test.etl_synthea_dbt.not_null_visit_occurrence_visit_start_date.6ef645340a"}, {"status": "pass", "timing": [{"name": "compile", "started_at": "2023-09-25T13:12:11.631299Z", "completed_at": "2023-09-25T13:12:11.635250Z"}, {"name": "execute", "started_at": "2023-09-25T13:12:11.635630Z", "completed_at": "2023-09-25T13:12:11.644208Z"}], "thread_id": "Thread-1 (worker)", "execution_time": 0.015484094619750977, "adapter_response": {"_message": "OK"}, "message": null, "failures": 0, "unique_id": "test.etl_synthea_dbt.not_null_visit_occurrence_visit_type_concept_id.6078890882"}, {"status": "pass", "timing": [{"name": "compile", "started_at": "2023-09-25T13:12:11.648004Z", "completed_at": "2023-09-25T13:12:11.651126Z"}, {"name": "execute", "started_at": "2023-09-25T13:12:11.651492Z", "completed_at": "2023-09-25T13:12:11.659853Z"}], "thread_id": "Thread-1 (worker)", "execution_time": 0.014367818832397461, "adapter_response": {"_message": "OK"}, "message": null, "failures": 0, "unique_id": "test.etl_synthea_dbt.relationships_device_exposure_visit_occurrence_id__visit_occurrence_id__ref_visit_occurrence_.c993394705"}, {"status": "pass", "timing": [{"name": "compile", "started_at": "2023-09-25T13:12:11.663189Z", "completed_at": "2023-09-25T13:12:11.666519Z"}, {"name": "execute", "started_at": "2023-09-25T13:12:11.666908Z", "completed_at": "2023-09-25T13:12:11.675337Z"}], "thread_id": "Thread-1 (worker)", "execution_time": 0.014725208282470703, "adapter_response": {"_message": "OK"}, "message": null, "failures": 0, "unique_id": "test.etl_synthea_dbt.relationships_drug_exposure_visit_occurrence_id__visit_occurrence_id__ref_visit_occurrence_.a7ed7dfcb5"}, {"status": "pass", "timing": [{"name": "compile", "started_at": "2023-09-25T13:12:11.678929Z", "completed_at": "2023-09-25T13:12:11.682028Z"}, {"name": "execute", "started_at": "2023-09-25T13:12:11.682577Z", "completed_at": "2023-09-25T13:12:11.690723Z"}], "thread_id": "Thread-1 (worker)", "execution_time": 0.014447212219238281, "adapter_response": {"_message": "OK"}, "message": null, "failures": 0, "unique_id": "test.etl_synthea_dbt.relationships_measurement_visit_occurrence_id__visit_occurrence_id__ref_visit_occurrence_.4fb747555a"}, {"status": "pass", "timing": [{"name": "compile", "started_at": "2023-09-25T13:12:11.694515Z", "completed_at": "2023-09-25T13:12:11.697459Z"}, {"name": "execute", "started_at": "2023-09-25T13:12:11.697854Z", "completed_at": "2023-09-25T13:12:11.706678Z"}], "thread_id": "Thread-1 (worker)", "execution_time": 0.014787912368774414, "adapter_response": {"_message": "OK"}, "message": null, "failures": 0, "unique_id": "test.etl_synthea_dbt.relationships_observation_visit_occurrence_id__visit_occurrence_id__ref_visit_occurrence_.6929746e26"}, {"status": "pass", "timing": [{"name": "compile", "started_at": "2023-09-25T13:12:11.710497Z", "completed_at": "2023-09-25T13:12:11.713267Z"}, {"name": "execute", "started_at": "2023-09-25T13:12:11.713644Z", "completed_at": "2023-09-25T13:12:11.722609Z"}], "thread_id": "Thread-1 (worker)", "execution_time": 0.014885902404785156, "adapter_response": {"_message": "OK"}, "message": null, "failures": 0, "unique_id": "test.etl_synthea_dbt.relationships_procedure_occurrence_visit_occurrence_id__visit_occurrence_id__ref_visit_occurrence_.57f0006526"}, {"status": "pass", "timing": [{"name": "compile", "started_at": "2023-09-25T13:12:11.726430Z", "completed_at": "2023-09-25T13:12:11.729304Z"}, {"name": "execute", "started_at": "2023-09-25T13:12:11.729710Z", "completed_at": "2023-09-25T13:12:11.769655Z"}], "thread_id": "Thread-1 (worker)", "execution_time": 0.04661893844604492, "adapter_response": {"_message": "OK"}, "message": null, "failures": 0, "unique_id": "test.etl_synthea_dbt.relationships_visit_occurrence_admitting_source_concept_id__concept_id__source_vocab_concept_.ee5b624dfe"}, {"status": "pass", "timing": [{"name": "compile", "started_at": "2023-09-25T13:12:11.774311Z", "completed_at": "2023-09-25T13:12:11.777009Z"}, {"name": "execute", "started_at": "2023-09-25T13:12:11.777365Z", "completed_at": "2023-09-25T13:12:11.815767Z"}], "thread_id": "Thread-1 (worker)", "execution_time": 0.04415607452392578, "adapter_response": {"_message": "OK"}, "message": null, "failures": 0, "unique_id": "test.etl_synthea_dbt.relationships_visit_occurrence_discharge_to_concept_id__concept_id__source_vocab_concept_.2f4c28e6b1"}, {"status": "pass", "timing": [{"name": "compile", "started_at": "2023-09-25T13:12:11.819317Z", "completed_at": "2023-09-25T13:12:11.821946Z"}, {"name": "execute", "started_at": "2023-09-25T13:12:11.822293Z", "completed_at": "2023-09-25T13:12:11.830988Z"}], "thread_id": "Thread-1 (worker)", "execution_time": 0.014091014862060547, "adapter_response": {"_message": "OK"}, "message": null, "failures": 0, "unique_id": "test.etl_synthea_dbt.relationships_visit_occurrence_person_id__person_id__ref_person_.0f12e4784d"}, {"status": "pass", "timing": [{"name": "compile", "started_at": "2023-09-25T13:12:11.834361Z", "completed_at": "2023-09-25T13:12:11.837203Z"}, {"name": "execute", "started_at": "2023-09-25T13:12:11.837555Z", "completed_at": "2023-09-25T13:12:11.852796Z"}], "thread_id": "Thread-1 (worker)", "execution_time": 0.021637678146362305, "adapter_response": {"_message": "OK"}, "message": null, "failures": 0, "unique_id": "test.etl_synthea_dbt.relationships_visit_occurrence_preceding_visit_occurrence_id__visit_occurrence_id__ref_visit_occurrence_.df91dec380"}, {"status": "pass", "timing": [{"name": "compile", "started_at": "2023-09-25T13:12:11.857419Z", "completed_at": "2023-09-25T13:12:11.860555Z"}, {"name": "execute", "started_at": "2023-09-25T13:12:11.860974Z", "completed_at": "2023-09-25T13:12:11.898547Z"}], "thread_id": "Thread-1 (worker)", "execution_time": 0.04395604133605957, "adapter_response": {"_message": "OK"}, "message": null, "failures": 0, "unique_id": "test.etl_synthea_dbt.relationships_visit_occurrence_visit_concept_id__concept_id__source_vocab_concept_.989bda5e7b"}, {"status": "pass", "timing": [{"name": "compile", "started_at": "2023-09-25T13:12:11.902009Z", "completed_at": "2023-09-25T13:12:11.904660Z"}, {"name": "execute", "started_at": "2023-09-25T13:12:11.905022Z", "completed_at": "2023-09-25T13:12:11.943495Z"}], "thread_id": "Thread-1 (worker)", "execution_time": 0.04414176940917969, "adapter_response": {"_message": "OK"}, "message": null, "failures": 0, "unique_id": "test.etl_synthea_dbt.relationships_visit_occurrence_visit_type_concept_id__concept_id__source_vocab_concept_.de192d0d82"}, {"status": "pass", "timing": [{"name": "compile", "started_at": "2023-09-25T13:12:11.947323Z", "completed_at": "2023-09-25T13:12:11.949705Z"}, {"name": "execute", "started_at": "2023-09-25T13:12:11.950069Z", "completed_at": "2023-09-25T13:12:11.962049Z"}], "thread_id": "Thread-1 (worker)", "execution_time": 0.017448902130126953, "adapter_response": {"_message": "OK"}, "message": null, "failures": 0, "unique_id": "test.etl_synthea_dbt.unique_visit_occurrence_visit_occurrence_id.faa3aa67c6"}, {"status": "success", "timing": [{"name": "compile", "started_at": "2023-09-25T13:12:11.965929Z", "completed_at": "2023-09-25T13:12:11.969423Z"}, {"name": "execute", "started_at": "2023-09-25T13:12:11.969765Z", "completed_at": "2023-09-25T13:12:11.991953Z"}], "thread_id": "Thread-1 (worker)", "execution_time": 0.03139185905456543, "adapter_response": {"_message": "OK"}, "message": "OK", "failures": null, "unique_id": "model.etl_synthea_dbt.tmp_de"}, {"status": "pass", "timing": [{"name": "compile", "started_at": "2023-09-25T13:12:11.998602Z", "completed_at": "2023-09-25T13:12:12.000910Z"}, {"name": "execute", "started_at": "2023-09-25T13:12:12.001270Z", "completed_at": "2023-09-25T13:12:12.008406Z"}], "thread_id": "Thread-1 (worker)", "execution_time": 0.012967109680175781, "adapter_response": {"_message": "OK"}, "message": null, "failures": 0, "unique_id": "test.etl_synthea_dbt.not_null_condition_occurrence_condition_occurrence_id.f70111fa08"}, {"status": "pass", "timing": [{"name": "compile", "started_at": "2023-09-25T13:12:12.012566Z", "completed_at": "2023-09-25T13:12:12.014939Z"}, {"name": "execute", "started_at": "2023-09-25T13:12:12.015301Z", "completed_at": "2023-09-25T13:12:12.022561Z"}], "thread_id": "Thread-1 (worker)", "execution_time": 0.013067960739135742, "adapter_response": {"_message": "OK"}, "message": null, "failures": 0, "unique_id": "test.etl_synthea_dbt.not_null_condition_occurrence_condition_start_date.6cbb11717a"}, {"status": "pass", "timing": [{"name": "compile", "started_at": "2023-09-25T13:12:12.026733Z", "completed_at": "2023-09-25T13:12:12.029194Z"}, {"name": "execute", "started_at": "2023-09-25T13:12:12.029537Z", "completed_at": "2023-09-25T13:12:12.037020Z"}], "thread_id": "Thread-1 (worker)", "execution_time": 0.01349186897277832, "adapter_response": {"_message": "OK"}, "message": null, "failures": 0, "unique_id": "test.etl_synthea_dbt.not_null_condition_occurrence_condition_type_concept_id.13b95f8e19"}, {"status": "pass", "timing": [{"name": "compile", "started_at": "2023-09-25T13:12:12.041336Z", "completed_at": "2023-09-25T13:12:12.043798Z"}, {"name": "execute", "started_at": "2023-09-25T13:12:12.044268Z", "completed_at": "2023-09-25T13:12:12.052558Z"}], "thread_id": "Thread-1 (worker)", "execution_time": 0.013602018356323242, "adapter_response": {"_message": "OK"}, "message": null, "failures": 0, "unique_id": "test.etl_synthea_dbt.not_null_condition_occurrence_person_id.9f19d9c9cb"}, {"status": "pass", "timing": [{"name": "compile", "started_at": "2023-09-25T13:12:12.056029Z", "completed_at": "2023-09-25T13:12:12.059132Z"}, {"name": "execute", "started_at": "2023-09-25T13:12:12.059506Z", "completed_at": "2023-09-25T13:12:12.069236Z"}], "thread_id": "Thread-1 (worker)", "execution_time": 0.015688180923461914, "adapter_response": {"_message": "OK"}, "message": null, "failures": 0, "unique_id": "test.etl_synthea_dbt.relationships_condition_occurrence_condition_concept_id__concept_id__source_vocab_concept_.d920e04abd"}, {"status": "pass", "timing": [{"name": "compile", "started_at": "2023-09-25T13:12:12.072743Z", "completed_at": "2023-09-25T13:12:12.075669Z"}, {"name": "execute", "started_at": "2023-09-25T13:12:12.076052Z", "completed_at": "2023-09-25T13:12:12.083910Z"}], "thread_id": "Thread-1 (worker)", "execution_time": 0.01393890380859375, "adapter_response": {"_message": "OK"}, "message": null, "failures": 0, "unique_id": "test.etl_synthea_dbt.relationships_condition_occurrence_condition_source_concept_id__concept_id__source_vocab_concept_.1f641311f0"}, {"status": "pass", "timing": [{"name": "compile", "started_at": "2023-09-25T13:12:12.087795Z", "completed_at": "2023-09-25T13:12:12.090739Z"}, {"name": "execute", "started_at": "2023-09-25T13:12:12.091119Z", "completed_at": "2023-09-25T13:12:12.099545Z"}], "thread_id": "Thread-1 (worker)", "execution_time": 0.014335870742797852, "adapter_response": {"_message": "OK"}, "message": null, "failures": 0, "unique_id": "test.etl_synthea_dbt.relationships_condition_occurrence_condition_status_source_value__concept_id__source_vocab_concept_.05a987e39c"}, {"status": "pass", "timing": [{"name": "compile", "started_at": "2023-09-25T13:12:12.103254Z", "completed_at": "2023-09-25T13:12:12.106249Z"}, {"name": "execute", "started_at": "2023-09-25T13:12:12.106634Z", "completed_at": "2023-09-25T13:12:12.115179Z"}], "thread_id": "Thread-1 (worker)", "execution_time": 0.01451730728149414, "adapter_response": {"_message": "OK"}, "message": null, "failures": 0, "unique_id": "test.etl_synthea_dbt.relationships_condition_occurrence_condition_type_concept_id__concept_id__source_vocab_concept_.42f881e4a7"}, {"status": "pass", "timing": [{"name": "compile", "started_at": "2023-09-25T13:12:12.118748Z", "completed_at": "2023-09-25T13:12:12.121441Z"}, {"name": "execute", "started_at": "2023-09-25T13:12:12.121792Z", "completed_at": "2023-09-25T13:12:12.129810Z"}], "thread_id": "Thread-1 (worker)", "execution_time": 0.014370203018188477, "adapter_response": {"_message": "OK"}, "message": null, "failures": 0, "unique_id": "test.etl_synthea_dbt.relationships_condition_occurrence_person_id__person_id__ref_person_.f3b716ae22"}, {"status": "pass", "timing": [{"name": "compile", "started_at": "2023-09-25T13:12:12.134476Z", "completed_at": "2023-09-25T13:12:12.137274Z"}, {"name": "execute", "started_at": "2023-09-25T13:12:12.137634Z", "completed_at": "2023-09-25T13:12:12.145377Z"}], "thread_id": "Thread-1 (worker)", "execution_time": 0.013342857360839844, "adapter_response": {"_message": "OK"}, "message": null, "failures": 0, "unique_id": "test.etl_synthea_dbt.relationships_condition_occurrence_provider_id__provider_id__ref_provider_.b75b05445b"}, {"status": "pass", "timing": [{"name": "compile", "started_at": "2023-09-25T13:12:12.148932Z", "completed_at": "2023-09-25T13:12:12.151790Z"}, {"name": "execute", "started_at": "2023-09-25T13:12:12.152154Z", "completed_at": "2023-09-25T13:12:12.159930Z"}], "thread_id": "Thread-1 (worker)", "execution_time": 0.013473749160766602, "adapter_response": {"_message": "OK"}, "message": null, "failures": 0, "unique_id": "test.etl_synthea_dbt.relationships_condition_occurrence_visit_detail_id__visit_detail_id__ref_visit_detail_.fc073d5579"}, {"status": "pass", "timing": [{"name": "compile", "started_at": "2023-09-25T13:12:12.163438Z", "completed_at": "2023-09-25T13:12:12.166540Z"}, {"name": "execute", "started_at": "2023-09-25T13:12:12.166920Z", "completed_at": "2023-09-25T13:12:12.176147Z"}], "thread_id": "Thread-1 (worker)", "execution_time": 0.015834808349609375, "adapter_response": {"_message": "OK"}, "message": null, "failures": 0, "unique_id": "test.etl_synthea_dbt.relationships_condition_occurrence_visit_occurrence_id__visit_occurrence_id__ref_visit_occurrence_.2e469f049b"}, {"status": "pass", "timing": [{"name": "compile", "started_at": "2023-09-25T13:12:12.180259Z", "completed_at": "2023-09-25T13:12:12.182740Z"}, {"name": "execute", "started_at": "2023-09-25T13:12:12.183112Z", "completed_at": "2023-09-25T13:12:12.190557Z"}], "thread_id": "Thread-1 (worker)", "execution_time": 0.012872934341430664, "adapter_response": {"_message": "OK"}, "message": null, "failures": 0, "unique_id": "test.etl_synthea_dbt.unique_condition_occurrence_condition_occurrence_id.e4cb792f90"}, {"status": "success", "timing": [{"name": "compile", "started_at": "2023-09-25T13:12:12.194239Z", "completed_at": "2023-09-25T13:12:12.195818Z"}, {"name": "execute", "started_at": "2023-09-25T13:12:12.196164Z", "completed_at": "2023-09-25T13:12:12.230216Z"}], "thread_id": "Thread-1 (worker)", "execution_time": 0.04132699966430664, "adapter_response": {"_message": "OK"}, "message": "OK", "failures": null, "unique_id": "model.etl_synthea_dbt.drug_era"}, {"status": "success", "timing": [{"name": "compile", "started_at": "2023-09-25T13:12:12.236730Z", "completed_at": "2023-09-25T13:12:12.238581Z"}, {"name": "execute", "started_at": "2023-09-25T13:12:12.238904Z", "completed_at": "2023-09-25T13:12:12.254072Z"}], "thread_id": "Thread-1 (worker)", "execution_time": 0.022739171981811523, "adapter_response": {"_message": "OK"}, "message": "OK", "failures": null, "unique_id": "model.etl_synthea_dbt.tmp_ce"}, {"status": "pass", "timing": [{"name": "compile", "started_at": "2023-09-25T13:12:12.260794Z", "completed_at": "2023-09-25T13:12:12.264290Z"}, {"name": "execute", "started_at": "2023-09-25T13:12:12.264675Z", "completed_at": "2023-09-25T13:12:12.273183Z"}], "thread_id": "Thread-1 (worker)", "execution_time": 0.015041828155517578, "adapter_response": {"_message": "OK"}, "message": null, "failures": 0, "unique_id": "test.etl_synthea_dbt.not_null_drug_era_drug_concept_id.f7daf926d4"}, {"status": "pass", "timing": [{"name": "compile", "started_at": "2023-09-25T13:12:12.276694Z", "completed_at": "2023-09-25T13:12:12.278755Z"}, {"name": "execute", "started_at": "2023-09-25T13:12:12.279081Z", "completed_at": "2023-09-25T13:12:12.286775Z"}], "thread_id": "Thread-1 (worker)", "execution_time": 0.01314687728881836, "adapter_response": {"_message": "OK"}, "message": null, "failures": 0, "unique_id": "test.etl_synthea_dbt.not_null_drug_era_drug_era_end_date.ec78b5bf14"}, {"status": "pass", "timing": [{"name": "compile", "started_at": "2023-09-25T13:12:12.290883Z", "completed_at": "2023-09-25T13:12:12.293196Z"}, {"name": "execute", "started_at": "2023-09-25T13:12:12.293531Z", "completed_at": "2023-09-25T13:12:12.300937Z"}], "thread_id": "Thread-1 (worker)", "execution_time": 0.012486934661865234, "adapter_response": {"_message": "OK"}, "message": null, "failures": 0, "unique_id": "test.etl_synthea_dbt.not_null_drug_era_drug_era_id.69fa2cd6fe"}, {"status": "pass", "timing": [{"name": "compile", "started_at": "2023-09-25T13:12:12.304186Z", "completed_at": "2023-09-25T13:12:12.306618Z"}, {"name": "execute", "started_at": "2023-09-25T13:12:12.306992Z", "completed_at": "2023-09-25T13:12:12.314512Z"}], "thread_id": "Thread-1 (worker)", "execution_time": 0.013453245162963867, "adapter_response": {"_message": "OK"}, "message": null, "failures": 0, "unique_id": "test.etl_synthea_dbt.not_null_drug_era_drug_era_start_date.7321b828f3"}, {"status": "pass", "timing": [{"name": "compile", "started_at": "2023-09-25T13:12:12.318651Z", "completed_at": "2023-09-25T13:12:12.320936Z"}, {"name": "execute", "started_at": "2023-09-25T13:12:12.321279Z", "completed_at": "2023-09-25T13:12:12.328607Z"}], "thread_id": "Thread-1 (worker)", "execution_time": 0.013026714324951172, "adapter_response": {"_message": "OK"}, "message": null, "failures": 0, "unique_id": "test.etl_synthea_dbt.not_null_drug_era_person_id.e848e282a5"}, {"status": "pass", "timing": [{"name": "compile", "started_at": "2023-09-25T13:12:12.332830Z", "completed_at": "2023-09-25T13:12:12.335613Z"}, {"name": "execute", "started_at": "2023-09-25T13:12:12.335986Z", "completed_at": "2023-09-25T13:12:12.343930Z"}], "thread_id": "Thread-1 (worker)", "execution_time": 0.01361083984375, "adapter_response": {"_message": "OK"}, "message": null, "failures": 0, "unique_id": "test.etl_synthea_dbt.relationships_drug_era_drug_concept_id__concept_id__source_vocab_concept_.91ffe5fbde"}, {"status": "pass", "timing": [{"name": "compile", "started_at": "2023-09-25T13:12:12.347619Z", "completed_at": "2023-09-25T13:12:12.350444Z"}, {"name": "execute", "started_at": "2023-09-25T13:12:12.350821Z", "completed_at": "2023-09-25T13:12:12.359422Z"}], "thread_id": "Thread-1 (worker)", "execution_time": 0.014395952224731445, "adapter_response": {"_message": "OK"}, "message": null, "failures": 0, "unique_id": "test.etl_synthea_dbt.relationships_drug_era_person_id__person_id__ref_person_.a3cad7938a"}, {"status": "pass", "timing": [{"name": "compile", "started_at": "2023-09-25T13:12:12.362987Z", "completed_at": "2023-09-25T13:12:12.366825Z"}, {"name": "execute", "started_at": "2023-09-25T13:12:12.367197Z", "completed_at": "2023-09-25T13:12:12.375598Z"}], "thread_id": "Thread-1 (worker)", "execution_time": 0.015127182006835938, "adapter_response": {"_message": "OK"}, "message": null, "failures": 0, "unique_id": "test.etl_synthea_dbt.unique_drug_era_drug_era_id.e3b01c38b2"}, {"status": "success", "timing": [{"name": "compile", "started_at": "2023-09-25T13:12:12.379109Z", "completed_at": "2023-09-25T13:12:12.381115Z"}, {"name": "execute", "started_at": "2023-09-25T13:12:12.381506Z", "completed_at": "2023-09-25T13:12:12.399992Z"}], "thread_id": "Thread-1 (worker)", "execution_time": 0.026626110076904297, "adapter_response": {"_message": "OK"}, "message": "OK", "failures": null, "unique_id": "model.etl_synthea_dbt.condition_era"}, {"status": "pass", "timing": [{"name": "compile", "started_at": "2023-09-25T13:12:12.407845Z", "completed_at": "2023-09-25T13:12:12.410143Z"}, {"name": "execute", "started_at": "2023-09-25T13:12:12.410549Z", "completed_at": "2023-09-25T13:12:12.418961Z"}], "thread_id": "Thread-1 (worker)", "execution_time": 0.013848066329956055, "adapter_response": {"_message": "OK"}, "message": null, "failures": 0, "unique_id": "test.etl_synthea_dbt.not_null_condition_era_condition_concept_id.e3da2b562c"}, {"status": "pass", "timing": [{"name": "compile", "started_at": "2023-09-25T13:12:12.422661Z", "completed_at": "2023-09-25T13:12:12.425230Z"}, {"name": "execute", "started_at": "2023-09-25T13:12:12.425606Z", "completed_at": "2023-09-25T13:12:12.433592Z"}], "thread_id": "Thread-1 (worker)", "execution_time": 0.013509988784790039, "adapter_response": {"_message": "OK"}, "message": null, "failures": 0, "unique_id": "test.etl_synthea_dbt.not_null_condition_era_condition_era_end_date.de0da8b839"}, {"status": "pass", "timing": [{"name": "compile", "started_at": "2023-09-25T13:12:12.437117Z", "completed_at": "2023-09-25T13:12:12.439573Z"}, {"name": "execute", "started_at": "2023-09-25T13:12:12.440018Z", "completed_at": "2023-09-25T13:12:12.447450Z"}], "thread_id": "Thread-1 (worker)", "execution_time": 0.012951135635375977, "adapter_response": {"_message": "OK"}, "message": null, "failures": 0, "unique_id": "test.etl_synthea_dbt.not_null_condition_era_condition_era_id.7a62c16f99"}, {"status": "pass", "timing": [{"name": "compile", "started_at": "2023-09-25T13:12:12.451141Z", "completed_at": "2023-09-25T13:12:12.454661Z"}, {"name": "execute", "started_at": "2023-09-25T13:12:12.455044Z", "completed_at": "2023-09-25T13:12:12.463448Z"}], "thread_id": "Thread-1 (worker)", "execution_time": 0.014763116836547852, "adapter_response": {"_message": "OK"}, "message": null, "failures": 0, "unique_id": "test.etl_synthea_dbt.not_null_condition_era_condition_era_start_date.479245d393"}, {"status": "pass", "timing": [{"name": "compile", "started_at": "2023-09-25T13:12:12.466798Z", "completed_at": "2023-09-25T13:12:12.468988Z"}, {"name": "execute", "started_at": "2023-09-25T13:12:12.469329Z", "completed_at": "2023-09-25T13:12:12.477867Z"}], "thread_id": "Thread-1 (worker)", "execution_time": 0.013524055480957031, "adapter_response": {"_message": "OK"}, "message": null, "failures": 0, "unique_id": "test.etl_synthea_dbt.not_null_condition_era_person_id.0c539c09d2"}, {"status": "pass", "timing": [{"name": "compile", "started_at": "2023-09-25T13:12:12.481277Z", "completed_at": "2023-09-25T13:12:12.484301Z"}, {"name": "execute", "started_at": "2023-09-25T13:12:12.484672Z", "completed_at": "2023-09-25T13:12:12.493044Z"}], "thread_id": "Thread-1 (worker)", "execution_time": 0.01416015625, "adapter_response": {"_message": "OK"}, "message": null, "failures": 0, "unique_id": "test.etl_synthea_dbt.relationships_condition_era_condition_concept_id__concept_id__source_vocab_concept_.3e586bc15f"}, {"status": "pass", "timing": [{"name": "compile", "started_at": "2023-09-25T13:12:12.496417Z", "completed_at": "2023-09-25T13:12:12.499358Z"}, {"name": "execute", "started_at": "2023-09-25T13:12:12.499736Z", "completed_at": "2023-09-25T13:12:12.507541Z"}], "thread_id": "Thread-1 (worker)", "execution_time": 0.01379704475402832, "adapter_response": {"_message": "OK"}, "message": null, "failures": 0, "unique_id": "test.etl_synthea_dbt.relationships_condition_era_person_id__person_id__ref_person_.e1a24435e6"}, {"status": "pass", "timing": [{"name": "compile", "started_at": "2023-09-25T13:12:12.511043Z", "completed_at": "2023-09-25T13:12:12.513348Z"}, {"name": "execute", "started_at": "2023-09-25T13:12:12.513717Z", "completed_at": "2023-09-25T13:12:12.521651Z"}], "thread_id": "Thread-1 (worker)", "execution_time": 0.013163089752197266, "adapter_response": {"_message": "OK"}, "message": null, "failures": 0, "unique_id": "test.etl_synthea_dbt.unique_condition_era_condition_era_id.cd3b6005dd"}], "elapsed_time": 17.75712490081787, "args": {"show": false, "profiles_dir": "/Users/leizhou/dev/data_proj/astro_cosmos_omop/dags/dbt/ETL-Synthea-dbt", "warn_error_options": {"include": [], "exclude": []}, "invocation_command": "dbt build", "version_check": true, "write_json": true, "introspect": true, "partial_parse_file_diff": true, "populate_cache": true, "static_parser": true, "vars": {}, "log_format": "default", "select": [], "project_dir": "/Users/leizhou/dev/data_proj/astro_cosmos_omop/dags/dbt/ETL-Synthea-dbt", "send_anonymous_usage_stats": true, "log_file_max_bytes": 10485760, "macro_debugging": false, "log_format_file": "debug", "partial_parse": true, "exclude": [], "log_path": "/Users/leizhou/dev/data_proj/astro_cosmos_omop/dags/dbt/ETL-Synthea-dbt/logs", "enable_legacy_logger": false, "use_colors_file": true, "log_level_file": "debug", "which": "build", "log_level": "info", "printer_width": 80, "indirect_selection": "eager", "cache_selected_only": false, "use_colors": true, "quiet": false, "resource_types": [], "strict_mode": false, "favor_state": false, "print": true, "defer": false}}